<?xml version="1.0"?>
<?xml-stylesheet type='text/xsl' href='MessageLog.xsl'?>
<Log FirstSessionID="1" LastSessionID="12"><Message Date="29/09/2006" Time="12:24:32 PM" DateTime="2006-09-29T02:24:32.453Z" SessionID="1"><From><User FriendlyName="- James (L)s Alison----I Welcome thee back Widget! :D"/></From><To><User FriendlyName="MMXII"/></To><Text Style="font-family:Microsoft Sans Serif; color:#000000; ">that avatar going on PCPP too :P</Text></Message><Message Date="7/03/2007" Time="7:31:28 PM" DateTime="2007-03-07T08:31:28.000Z" SessionID="2"><From><User FriendlyName="- James(&amp;) Charmed!"/></From><To><User FriendlyName="...."/></To><Text Style="font-family:Microsoft Sans Serif; color:#000000; ">I'll take two!</Text></Message><Message Date="7/03/2007" Time="7:31:40 PM" DateTime="2007-03-07T08:31:40.638Z" SessionID="3"><From><User FriendlyName="...."/></From><To><User FriendlyName="- James(&amp;) Charmed!"/></To><Text Style="font-family:Microsoft Sans Serif; color:#000080; ">okay</Text></Message><Message Date="7/03/2007" Time="7:31:52 PM" DateTime="2007-03-07T08:31:52.516Z" SessionID="3"><From><User FriendlyName="- James(&amp;) Charmed!"/></From><To><User FriendlyName="...."/></To><Text Style="font-family:Microsoft Sans Serif; color:#000000; ">----------------------------------------&gt;</Text></Message><Message Date="28/04/2007" Time="1:25:05 PM" DateTime="2007-04-28T03:25:05.009Z" SessionID="4"><From><User FriendlyName="- James (&amp;)  Charmed --- I own a UniCycle AND POKEMON PEARL!"/></From><To><User FriendlyName="..........."/></To><Text Style="font-family:Microsoft Sans Serif; color:#000000; ">Nice Storage</Text></Message><Message Date="28/04/2007" Time="1:25:33 PM" DateTime="2007-04-28T03:25:33.789Z" SessionID="4"><From><User FriendlyName="..........."/></From><To><User FriendlyName="- James (&amp;)  Charmed --- I own a UniCycle AND POKEMON PEARL!"/></To><Text Style="font-family:Microsoft Sans Serif; color:#000080; ">tis</Text></Message><Message Date="28/04/2007" Time="1:26:39 PM" DateTime="2007-04-28T03:26:39.481Z" SessionID="4"><From><User FriendlyName="- James (&amp;)  Charmed --- I own a UniCycle AND POKEMON PEARL!"/></From><To><User FriendlyName="..........."/></To><Text Style="font-family:Microsoft Sans Serif; color:#000000; ">By the way, wheres the pic from?</Text></Message><Message Date="28/04/2007" Time="1:27:27 PM" DateTime="2007-04-28T03:27:27.001Z" SessionID="5"><From><User FriendlyName="..........."/></From><To><User FriendlyName="- James (&amp;)  Charmed --- I own a UniCycle AND POKEMON PEARL!"/></To><Text Style="font-family:Microsoft Sans Serif; color:#000080; ">this thing called "the internet"</Text></Message><Message Date="28/04/2007" Time="1:27:47 PM" DateTime="2007-04-28T03:27:47.545Z" SessionID="5"><From><User FriendlyName="- James (&amp;)  Charmed --- I own a UniCycle AND POKEMON PEARL!"/></From><To><User FriendlyName="..........."/></To><Text Style="font-family:Microsoft Sans Serif; color:#000000; ">Get outta town!</Text></Message><Message Date="28/04/2007" Time="1:27:59 PM" DateTime="2007-04-28T03:27:59.559Z" SessionID="5"><From><User FriendlyName="- James (&amp;)  Charmed --- I own a UniCycle AND POKEMON PEARL!"/></From><To><User FriendlyName="..........."/></To><Text Style="font-family:Microsoft Sans Serif; color:#000000; ">(Looks like its from like an indiana jones movie or something)</Text></Message><Message Date="28/04/2007" Time="1:29:49 PM" DateTime="2007-04-28T03:29:49.609Z" SessionID="5"><From><User FriendlyName="..........."/></From><To><User FriendlyName="- James (&amp;)  Charmed --- I own a UniCycle AND POKEMON PEARL!"/></To><Text Style="font-family:Microsoft Sans Serif; color:#000080; ">http://images.google.com.au/images?hl=en&amp;safe=off&amp;q=fully%20sikh&amp;btnG=Search&amp;ie=UTF-8&amp;oe=UTF-8&amp;um=1&amp;sa=N&amp;tab=wi</Text></Message><Message Date="28/04/2007" Time="1:30:33 PM" DateTime="2007-04-28T03:30:33.792Z" SessionID="5"><From><User FriendlyName="- James (&amp;)  Charmed --- I own a UniCycle AND POKEMON PEARL!"/></From><To><User FriendlyName="..........."/></To><Text Style="font-family:Microsoft Sans Serif; color:#000000; ">ahhh</Text></Message><Message Date="28/04/2007" Time="1:30:36 PM" DateTime="2007-04-28T03:30:36.397Z" SessionID="5"><From><User FriendlyName="- James (&amp;)  Charmed --- I own a UniCycle AND POKEMON PEARL!"/></From><To><User FriendlyName="..........."/></To><Text Style="font-family:Microsoft Sans Serif; color:#000000; ">haha neato</Text></Message><Message Date="1/10/2007" Time="11:10:32 AM" DateTime="2007-10-01T01:10:32.090Z" SessionID="6"><From><User FriendlyName="- *one James(&amp;) Geek - Unicycling FTW!"/></From><To><User FriendlyName="Mr. Google"/></To><Text Style="font-family:Microsoft Sans Serif; color:#000000; ">block</Text></Message><Message Date="28/01/2008" Time="12:51:55 PM" DateTime="2008-01-28T01:51:55.872Z" SessionID="7"><From><User FriendlyName="- *one James(&amp;) - Substitutiarylocomotion"/></From><To><User FriendlyName="Bobb Wylde"/></To><Text Style="font-family:Microsoft Sans Serif; color:#000000; ">/delete </Text></Message><Message Date="28/01/2008" Time="12:52:20 PM" DateTime="2008-01-28T01:52:20.702Z" SessionID="8"><From><User FriendlyName="Bobb Wylde"/></From><To><User FriendlyName="- *one James(&amp;) - Substitutiarylocomotion"/></To><Text Style="font-family:Trebuchet MS; font-weight:bold; color:#008000; ">?</Text></Message><Message Date="28/01/2008" Time="12:52:34 PM" DateTime="2008-01-28T01:52:34.549Z" SessionID="8"><From><User FriendlyName="- *one James(&amp;) - Substitutiarylocomotion"/></From><To><User FriendlyName="Bobb Wylde"/></To><Text Style="font-family:Microsoft Sans Serif; color:#000000; ">just lettingn u no</Text></Message><Message Date="28/01/2008" Time="12:52:39 PM" DateTime="2008-01-28T01:52:39.739Z" SessionID="8"><From><User FriendlyName="- *one James(&amp;) - Substitutiarylocomotion"/></From><To><User FriendlyName="Bobb Wylde"/></To><Text Style="font-family:Microsoft Sans Serif; color:#000000; ">That Im deleting u </Text></Message><Message Date="28/01/2008" Time="12:52:55 PM" DateTime="2008-01-28T01:52:55.600Z" SessionID="9"><From><User FriendlyName="Bobb Wylde"/></From><To><User FriendlyName="- *one James(&amp;) - Substitutiarylocomotion"/></To><Text Style="font-family:Trebuchet MS; font-weight:bold; color:#008000; ">good on ya</Text></Message><Message Date="28/01/2008" Time="12:53:03 PM" DateTime="2008-01-28T01:53:03.897Z" SessionID="9"><From><User FriendlyName="- *one James(&amp;) - Substitutiarylocomotion"/></From><To><User FriendlyName="Bobb Wylde"/></To><Text Style="font-family:Microsoft Sans Serif; color:#000000; ">cheers</Text></Message><Message Date="28/01/2008" Time="12:53:05 PM" DateTime="2008-01-28T01:53:05.188Z" SessionID="10"><From><User FriendlyName="Bobb Wylde"/></From><To><User FriendlyName="- *one James(&amp;) - Substitutiarylocomotion"/></To><Text Style="font-family:Trebuchet MS; font-weight:bold; color:#008000; ">;)</Text></Message><Message Date="28/01/2008" Time="12:53:10 PM" DateTime="2008-01-28T01:53:10.360Z" SessionID="10"><From><User FriendlyName="- *one James(&amp;) - Substitutiarylocomotion"/></From><To><User FriendlyName="Bobb Wylde"/></To><Text Style="font-family:Microsoft Sans Serif; color:#000000; ">Ave a good life</Text></Message><Message Date="28/01/2008" Time="12:53:34 PM" DateTime="2008-01-28T01:53:34.049Z" SessionID="11"><From><User FriendlyName="Bobb Wylde"/></From><To><User FriendlyName="- *one James(&amp;) - Substitutiarylocomotion"/></To><Text Style="font-family:Trebuchet MS; font-weight:bold; color:#008000; ">tanx</Text></Message><Message Date="6/3/2008" Time="3:38:44 PM" DateTime="2008-06-03T05:38:44.904Z" SessionID="12"><From><User FriendlyName="andy_millard@hotmail.com"/></From><To><User FriendlyName="Jeremy"/><User FriendlyName="aga"/><User FriendlyName="- James O'"/><User FriendlyName="(%) Big Nev"/><User FriendlyName="- mIsa / 'BloO! - Science! -"/><User FriendlyName="-2401- -Penitent Tangent- // Come save me, from walking off the window sill"/><User FriendlyName="Damien"/><User FriendlyName="]{ing-Nothing"/><User FriendlyName="[c=4]*DobB!3*  ///watch it burn let it die cos we are finally free tonight///[/c]   {watching a movie}"/><User FriendlyName="~r0kk3rz"/><User FriendlyName="Emmarrr(*)                                      iLOVEyouCARLY(L)                              (R)3 years...we finally made it(R)"/><User FriendlyName="Lance - Work work work"/><User FriendlyName="—(•·÷[   ßËÑJã(v)ÏÑ   ]÷·•)—"/><User FriendlyName="dillon"/><User FriendlyName="Adam:)"/><User FriendlyName="Alessandro"/><User FriendlyName="[S] a [M] m [I] :)"/><User FriendlyName="Dave"/><User FriendlyName="El'Burgo"/></To><Text Style="font-family:Segoe Script; color:#008000; ">hello all and welcome </Text></Message><Message Date="6/3/2008" Time="3:38:45 PM" DateTime="2008-06-03T05:38:45.215Z" SessionID="12"><From><User FriendlyName="andy_millard@hotmail.com"/></From><To><User FriendlyName="Jeremy"/><User FriendlyName="aga"/><User FriendlyName="- James O'"/><User FriendlyName="(%) Big Nev"/><User FriendlyName="- mIsa / 'BloO! - Science! -"/><User FriendlyName="-2401- -Penitent Tangent- // Come save me, from walking off the window sill"/><User FriendlyName="Damien"/><User FriendlyName="]{ing-Nothing"/><User FriendlyName="[c=4]*DobB!3*  ///watch it burn let it die cos we are finally free tonight///[/c]   {watching a movie}"/><User FriendlyName="~r0kk3rz"/><User FriendlyName="Emmarrr(*)                                      iLOVEyouCARLY(L)                              (R)3 years...we finally made it(R)"/><User FriendlyName="Lance - Work work work"/><User FriendlyName="—(•·÷[   ßËÑJã(v)ÏÑ   ]÷·•)—"/><User FriendlyName="dillon"/><User FriendlyName="Adam:)"/><User FriendlyName="Alessandro"/><User FriendlyName="[S] a [M] m [I] :)"/><User FriendlyName="Dave"/><User FriendlyName="El'Burgo"/></To><Text Style="font-family:Segoe Script; color:#008000; ">:D</Text></Message><Leave Date="6/3/2008" Time="3:38:52 PM" DateTime="2008-06-03T05:38:52.300Z" SessionID="12"><User FriendlyName="-2401- -Penitent Tangent- // Come save me, from walking off the window sill"/><Text Style="color:#800000; ">-2401- -Penitent Tangent- // Come save me, from walking off the window sill has left the conversation.</Text></Leave><Message Date="6/3/2008" Time="3:38:53 PM" DateTime="2008-06-03T05:38:53.354Z" SessionID="12"><From><User FriendlyName="andy_millard@hotmail.com"/></From><To><User FriendlyName="Jeremy"/><User FriendlyName="aga"/><User FriendlyName="- James O'"/><User FriendlyName="(%) Big Nev"/><User FriendlyName="- mIsa / 'BloO! - Science! -"/><User FriendlyName="Damien"/><User FriendlyName="]{ing-Nothing"/><User FriendlyName="[c=4]*DobB!3*  ///watch it burn let it die cos we are finally free tonight///[/c]   {watching a movie}"/><User FriendlyName="~r0kk3rz"/><User FriendlyName="Emmarrr(*)                                      iLOVEyouCARLY(L)                              (R)3 years...we finally made it(R)"/><User FriendlyName="Lance - Work work work"/><User FriendlyName="—(•·÷[   ßËÑJã(v)ÏÑ   ]÷·•)—"/><User FriendlyName="dillon"/><User FriendlyName="Adam:)"/><User FriendlyName="Alessandro"/><User FriendlyName="[S] a [M] m [I] :)"/><User FriendlyName="Dave"/><User FriendlyName="El'Burgo"/></To><Text Style="font-family:Segoe Script; color:#008000; ">i love gays</Text></Message><Leave Date="6/3/2008" Time="3:38:54 PM" DateTime="2008-06-03T05:38:54.591Z" SessionID="12"><User FriendlyName="Adam:)"/><Text Style="color:#800000; ">Adam:) has left the conversation.</Text></Leave><Message Date="6/3/2008" Time="3:38:56 PM" DateTime="2008-06-03T05:38:56.069Z" SessionID="12"><From><User FriendlyName="Lance - Work work work"/></From><To><User FriendlyName="Jeremy"/><User FriendlyName="aga"/><User FriendlyName="- James O'"/><User FriendlyName="(%) Big Nev"/><User FriendlyName="- mIsa / 'BloO! - Science! -"/><User FriendlyName="Damien"/><User FriendlyName="]{ing-Nothing"/><User FriendlyName="[c=4]*DobB!3*  ///watch it burn let it die cos we are finally free tonight///[/c]   {watching a movie}"/><User FriendlyName="~r0kk3rz"/><User FriendlyName="Emmarrr(*)                                      iLOVEyouCARLY(L)                              (R)3 years...we finally made it(R)"/><User FriendlyName="andy_millard@hotmail.com"/><User FriendlyName="—(•·÷[   ßËÑJã(v)ÏÑ   ]÷·•)—"/><User FriendlyName="dillon"/><User FriendlyName="Alessandro"/><User FriendlyName="[S] a [M] m [I] :)"/><User FriendlyName="Dave"/><User FriendlyName="El'Burgo"/></To><Text Style="font-family:Comic Sans MS; font-weight:bold; color:#0000ff; ">gtfo of my internet</Text></Message><Message Date="6/3/2008" Time="3:38:56 PM" DateTime="2008-06-03T05:38:56.866Z" SessionID="12"><From><User FriendlyName="andy_millard@hotmail.com"/></From><To><User FriendlyName="Jeremy"/><User FriendlyName="aga"/><User FriendlyName="- James O'"/><User FriendlyName="(%) Big Nev"/><User FriendlyName="- mIsa / 'BloO! - Science! -"/><User FriendlyName="Damien"/><User FriendlyName="]{ing-Nothing"/><User FriendlyName="[c=4]*DobB!3*  ///watch it burn let it die cos we are finally free tonight///[/c]   {watching a movie}"/><User FriendlyName="~r0kk3rz"/><User FriendlyName="Emmarrr(*)                                      iLOVEyouCARLY(L)                              (R)3 years...we finally made it(R)"/><User FriendlyName="Lance - Work work work"/><User FriendlyName="—(•·÷[   ßËÑJã(v)ÏÑ   ]÷·•)—"/><User FriendlyName="dillon"/><User FriendlyName="Alessandro"/><User FriendlyName="[S] a [M] m [I] :)"/><User FriendlyName="Dave"/><User FriendlyName="El'Burgo"/></To><Text Style="font-family:Segoe Script; color:#008000; ">i have to admit</Text></Message><Message Date="6/3/2008" Time="3:38:57 PM" DateTime="2008-06-03T05:38:57.030Z" SessionID="12"><From><User FriendlyName="dillon"/></From><To><User FriendlyName="Jeremy"/><User FriendlyName="aga"/><User FriendlyName="- James O'"/><User FriendlyName="(%) Big Nev"/><User FriendlyName="- mIsa / 'BloO! - Science! -"/><User FriendlyName="Damien"/><User FriendlyName="]{ing-Nothing"/><User FriendlyName="[c=4]*DobB!3*  ///watch it burn let it die cos we are finally free tonight///[/c]   {watching a movie}"/><User FriendlyName="~r0kk3rz"/><User FriendlyName="Emmarrr(*)                                      iLOVEyouCARLY(L)                              (R)3 years...we finally made it(R)"/><User FriendlyName="Lance - Work work work"/><User FriendlyName="andy_millard@hotmail.com"/><User FriendlyName="—(•·÷[   ßËÑJã(v)ÏÑ   ]÷·•)—"/><User FriendlyName="Alessandro"/><User FriendlyName="[S] a [M] m [I] :)"/><User FriendlyName="Dave"/><User FriendlyName="El'Burgo"/></To><Text Style="font-family:MS Shell Dlg; color:#000000; ">ahahahaha</Text></Message><Leave Date="6/3/2008" Time="3:38:57 PM" DateTime="2008-06-03T05:38:57.909Z" SessionID="12"><User FriendlyName="Jeremy"/><Text Style="color:#800000; ">Jeremy has left the conversation.</Text></Leave><Message Date="6/3/2008" Time="3:39:05 PM" DateTime="2008-06-03T05:39:05.680Z" SessionID="12"><From><User FriendlyName="andy_millard@hotmail.com"/></From><To><User FriendlyName="aga"/><User FriendlyName="- James O'"/><User FriendlyName="(%) Big Nev"/><User FriendlyName="- mIsa / 'BloO! - Science! -"/><User FriendlyName="Damien"/><User FriendlyName="]{ing-Nothing"/><User FriendlyName="[c=4]*DobB!3*  ///watch it burn let it die cos we are finally free tonight///[/c]   {watching a movie}"/><User FriendlyName="~r0kk3rz"/><User FriendlyName="Emmarrr(*)                                      iLOVEyouCARLY(L)                              (R)3 years...we finally made it(R)"/><User FriendlyName="Lance - Work work work"/><User FriendlyName="—(•·÷[   ßËÑJã(v)ÏÑ   ]÷·•)—"/><User FriendlyName="dillon"/><User FriendlyName="Alessandro"/><User FriendlyName="[S] a [M] m [I] :)"/><User FriendlyName="Dave"/><User FriendlyName="El'Burgo"/></To><Text Style="font-family:Segoe Script; color:#008000; ">illvea ll</Text></Message><Leave Date="6/3/2008" Time="3:39:10 PM" DateTime="2008-06-03T05:39:10.000Z" SessionID="12"><User FriendlyName="Lance - Work work work"/><Text Style="color:#800000; ">Lance - Work work work has left the conversation.</Text></Leave></Log>
