<?xml version="1.0"?>
<?xml-stylesheet type='text/xsl' href='MessageLog.xsl'?>
<Log FirstSessionID="1" LastSessionID="49"><Message Date="22/09/2004" Time="4:53:02 PM" DateTime="2004-09-22T06:53:02.124Z" SessionID="1"><From><User FriendlyName="erinleecarey@aol.com (E-mail Address Not Verified)"/></From><To><User FriendlyName="James*-)| Mac Killed My Inner Child..."/></To><Text Style="font-family:Papyrus; font-weight:bold; color:#ff00ff; ">hey</Text></Message><Message Date="22/09/2004" Time="4:53:08 PM" DateTime="2004-09-22T06:53:08.052Z" SessionID="1"><From><User FriendlyName="James*-)| Mac Killed My Inner Child..."/></From><To><User FriendlyName="erinleecarey@aol.com (E-mail Address Not Verified)"/></To><Text Style="font-family:Comic Sans MS; font-weight:bold; color:#000080; ">ah</Text></Message><Message Date="22/09/2004" Time="4:53:11 PM" DateTime="2004-09-22T06:53:11.828Z" SessionID="1"><From><User FriendlyName="James*-)| Mac Killed My Inner Child..."/></From><To><User FriendlyName="erinleecarey@aol.com (E-mail Address Not Verified)"/></To><Text Style="font-family:Comic Sans MS; font-weight:bold; color:#000080; ">Howdiho</Text></Message><Message Date="22/09/2004" Time="4:53:47 PM" DateTime="2004-09-22T06:53:47.079Z" SessionID="1"><From><User FriendlyName="James*-)| Mac Killed My Inner Child..."/></From><To><User FriendlyName="erinleecarey@aol.com (E-mail Address Not Verified)"/></To><Text Style="font-family:Comic Sans MS; font-weight:bold; color:#000080; ">ahh</Text></Message><Message Date="22/09/2004" Time="4:53:55 PM" DateTime="2004-09-22T06:53:55.070Z" SessionID="1"><From><User FriendlyName="erinleecarey@aol.com (E-mail Address Not Verified)"/></From><To><User FriendlyName="James*-)| Mac Killed My Inner Child..."/></To><Text Style="font-family:Papyrus; font-weight:bold; color:#ff00ff; ">y did u scream</Text></Message><Message Date="22/09/2004" Time="4:53:56 PM" DateTime="2004-09-22T06:53:56.051Z" SessionID="1"><From><User FriendlyName="James*-)| Mac Killed My Inner Child..."/></From><To><User FriendlyName="erinleecarey@aol.com (E-mail Address Not Verified)"/></To><Text Style="font-family:Comic Sans MS; font-weight:bold; color:#000080; ">one can only presume is erin</Text></Message><Message Date="22/09/2004" Time="4:54:01 PM" DateTime="2004-09-22T06:54:01.419Z" SessionID="1"><From><User FriendlyName="James*-)| Mac Killed My Inner Child..."/></From><To><User FriendlyName="erinleecarey@aol.com (E-mail Address Not Verified)"/></To><Text Style="font-family:Comic Sans MS; font-weight:bold; color:#000080; ">i scremed?</Text></Message><Message Date="22/09/2004" Time="4:54:09 PM" DateTime="2004-09-22T06:54:09.441Z" SessionID="1"><From><User FriendlyName="James*-)| Mac Killed My Inner Child..."/></From><To><User FriendlyName="erinleecarey@aol.com (E-mail Address Not Verified)"/></To><Text Style="font-family:Comic Sans MS; font-weight:bold; color:#000080; ">when</Text></Message><Message Date="22/09/2004" Time="4:54:17 PM" DateTime="2004-09-22T06:54:17.222Z" SessionID="1"><From><User FriendlyName="James*-)| Mac Killed My Inner Child..."/></From><To><User FriendlyName="erinleecarey@aol.com (E-mail Address Not Verified)"/></To><Text Style="font-family:Comic Sans MS; font-weight:bold; color:#000080; ">oh after maths?</Text></Message><Message Date="22/09/2004" Time="4:54:25 PM" DateTime="2004-09-22T06:54:25.424Z" SessionID="1"><From><User FriendlyName="James*-)| Mac Killed My Inner Child..."/></From><To><User FriendlyName="erinleecarey@aol.com (E-mail Address Not Verified)"/></To><Text Style="font-family:Comic Sans MS; font-weight:bold; color:#000080; ">There was a big ass stink bug on my hand</Text></Message><Message Date="22/09/2004" Time="4:54:27 PM" DateTime="2004-09-22T06:54:27.637Z" SessionID="1"><From><User FriendlyName="James*-)| Mac Killed My Inner Child..."/></From><To><User FriendlyName="erinleecarey@aol.com (E-mail Address Not Verified)"/></To><Text Style="font-family:Comic Sans MS; font-weight:bold; color:#000080; "> :)</Text></Message><Message Date="22/09/2004" Time="4:55:00 PM" DateTime="2004-09-22T06:55:00.664Z" SessionID="2"><From><User FriendlyName="erinleecarey@aol.com (E-mail Address Not Verified)"/></From><To><User FriendlyName="James*-)| Mac Killed My Inner Child..."/></To><Text Style="font-family:Papyrus; font-weight:bold; color:#ff00ff; ">um ok</Text></Message><Message Date="22/09/2004" Time="4:55:13 PM" DateTime="2004-09-22T06:55:13.813Z" SessionID="2"><From><User FriendlyName="James*-)| Mac Killed My Inner Child..."/></From><To><User FriendlyName="erinleecarey@aol.com (E-mail Address Not Verified)"/></To><Text Style="font-family:Comic Sans MS; font-weight:bold; color:#000080; ">:)</Text></Message><Message Date="24/09/2004" Time="3:37:36 PM" DateTime="2004-09-24T05:37:36.210Z" SessionID="3"><From><User FriendlyName="erinleecarey@aol.com (E-mail Address Not Verified)"/></From><To><User FriendlyName="James*-) On ventrilo, Channel, Port 3875, In americas army"/></To><Text Style="font-family:Papyrus; font-weight:bold; color:#ff00ff; ">hey</Text></Message><Message Date="24/09/2004" Time="3:38:16 PM" DateTime="2004-09-24T05:38:16.348Z" SessionID="3"><From><User FriendlyName="erinleecarey@aol.com (E-mail Address Not Verified)"/></From><To><User FriendlyName="James*-) On ventrilo, Channel, Port 3875, In americas army"/></To><Text Style="font-family:Papyrus; font-weight:bold; color:#ff00ff; ">?</Text></Message><Message Date="24/09/2004" Time="3:45:59 PM" DateTime="2004-09-24T05:45:59.684Z" SessionID="3"><From><User FriendlyName="James*-) On ventrilo, Channel, Port 3875, In americas army"/></From><To><User FriendlyName="erinleecarey@aol.com (E-mail Address Not Verified)"/></To><Text Style="font-family:Comic Sans MS; font-weight:bold; color:#000080; ">HAy soz cant talk</Text></Message><Message Date="24/09/2004" Time="7:22:55 PM" DateTime="2004-09-24T09:22:55.464Z" SessionID="4"><From><User FriendlyName="James*-)"/></From><To><User FriendlyName="erinleecarey@aol.com (E-mail Address Not Verified)"/></To><Text Style="font-family:Comic Sans MS; font-weight:bold; color:#000080; ">ullo</Text></Message><Message Date="24/09/2004" Time="7:23:07 PM" DateTime="2004-09-24T09:23:07.201Z" SessionID="5"><From><User FriendlyName="erinleecarey@aol.com (E-mail Address Not Verified)"/></From><To><User FriendlyName="James*-)"/></To><Text Style="font-family:Papyrus; font-weight:bold; color:#ff00ff; ">ullo ullo</Text></Message><Message Date="24/09/2004" Time="7:24:14 PM" DateTime="2004-09-24T09:24:14.758Z" SessionID="5"><From><User FriendlyName="erinleecarey@aol.com (E-mail Address Not Verified)"/></From><To><User FriendlyName="James*-)"/></To><Text Style="font-family:Papyrus; font-weight:bold; color:#ff00ff; ">got a nice ozie acent goin there</Text></Message><Message Date="24/09/2004" Time="7:24:23 PM" DateTime="2004-09-24T09:24:23.681Z" SessionID="5"><From><User FriendlyName="James*-)"/></From><To><User FriendlyName="erinleecarey@aol.com (E-mail Address Not Verified)"/></To><Text Style="font-family:Comic Sans MS; font-weight:bold; color:#000080; ">cheers</Text></Message><Message Date="24/09/2004" Time="7:24:35 PM" DateTime="2004-09-24T09:24:35.328Z" SessionID="5"><From><User FriendlyName="James*-)"/></From><To><User FriendlyName="erinleecarey@aol.com (E-mail Address Not Verified)"/></To><Text Style="font-family:Comic Sans MS; font-weight:bold; color:#000080; ">oi be right back i gotta finish making dinner</Text></Message><Message Date="24/09/2004" Time="7:24:35 PM" DateTime="2004-09-24T09:24:35.568Z" SessionID="5"><From><User FriendlyName="erinleecarey@aol.com (E-mail Address Not Verified)"/></From><To><User FriendlyName="James*-)"/></To><Text Style="font-family:Papyrus; font-weight:bold; color:#ff00ff; ">oh now its english</Text></Message><Message Date="24/09/2004" Time="7:24:36 PM" DateTime="2004-09-24T09:24:36.540Z" SessionID="5"><From><User FriendlyName="James*-)"/></From><To><User FriendlyName="erinleecarey@aol.com (E-mail Address Not Verified)"/></To><Text Style="font-family:Comic Sans MS; font-weight:bold; color:#000080; ">:)</Text></Message><Message Date="24/09/2004" Time="7:24:37 PM" DateTime="2004-09-24T09:24:37.932Z" SessionID="5"><From><User FriendlyName="James*-)"/></From><To><User FriendlyName="erinleecarey@aol.com (E-mail Address Not Verified)"/></To><Text Style="font-family:Comic Sans MS; font-weight:bold; color:#000080; ">yummy</Text></Message><Message Date="24/09/2004" Time="7:24:49 PM" DateTime="2004-09-24T09:24:49.548Z" SessionID="5"><From><User FriendlyName="James*-)"/></From><To><User FriendlyName="erinleecarey@aol.com (E-mail Address Not Verified)"/></To><Text Style="font-family:Comic Sans MS; font-weight:bold; color:#000080; ">and cheers in aussie</Text></Message><Message Date="24/09/2004" Time="7:29:27 PM" DateTime="2004-09-24T09:29:27.358Z" SessionID="6"><From><User FriendlyName="James*-)"/></From><To><User FriendlyName="erinleecarey@aol.com (E-mail Address Not Verified)"/></To><Text Style="font-family:Comic Sans MS; font-weight:bold; color:#000080; ">okyedokey Im baaaaack</Text></Message><Message Date="24/09/2004" Time="7:29:43 PM" DateTime="2004-09-24T09:29:43.942Z" SessionID="7"><From><User FriendlyName="erinleecarey@aol.com (E-mail Address Not Verified)"/></From><To><User FriendlyName="James*-)"/></To><Text Style="font-family:Papyrus; font-weight:bold; color:#ff00ff; ">coooooooooool</Text></Message><Message Date="24/09/2004" Time="7:29:52 PM" DateTime="2004-09-24T09:29:52.865Z" SessionID="7"><From><User FriendlyName="erinleecarey@aol.com (E-mail Address Not Verified)"/></From><To><User FriendlyName="James*-)"/></To><Text Style="font-family:Papyrus; font-weight:bold; color:#ff00ff; ">who do u like</Text></Message><Message Date="24/09/2004" Time="7:30:01 PM" DateTime="2004-09-24T09:30:01.837Z" SessionID="7"><From><User FriendlyName="erinleecarey@aol.com (E-mail Address Not Verified)"/></From><To><User FriendlyName="James*-)"/></To><Text Style="font-family:Papyrus; font-weight:bold; color:#ff00ff; ">i know u like sum1</Text></Message><Message Date="24/09/2004" Time="7:30:09 PM" DateTime="2004-09-24T09:30:09.559Z" SessionID="7"><From><User FriendlyName="erinleecarey@aol.com (E-mail Address Not Verified)"/></From><To><User FriendlyName="James*-)"/></To><Text Style="font-family:Papyrus; font-weight:bold; color:#ff00ff; ">just dont know who?</Text></Message><Message Date="24/09/2004" Time="7:30:12 PM" DateTime="2004-09-24T09:30:12.473Z" SessionID="7"><From><User FriendlyName="James*-)"/></From><To><User FriendlyName="erinleecarey@aol.com (E-mail Address Not Verified)"/></To><Text Style="font-family:Comic Sans MS; font-weight:bold; color:#000080; ">wow</Text></Message><Message Date="24/09/2004" Time="7:30:13 PM" DateTime="2004-09-24T09:30:13.274Z" SessionID="7"><From><User FriendlyName="James*-)"/></From><To><User FriendlyName="erinleecarey@aol.com (E-mail Address Not Verified)"/></To><Text Style="font-family:Comic Sans MS; font-weight:bold; color:#000080; ">u do</Text></Message><Message Date="24/09/2004" Time="7:30:23 PM" DateTime="2004-09-24T09:30:23.719Z" SessionID="7"><From><User FriendlyName="erinleecarey@aol.com (E-mail Address Not Verified)"/></From><To><User FriendlyName="James*-)"/></To><Text Style="font-family:Papyrus; font-weight:bold; color:#ff00ff; ">u do wat?</Text></Message><Message Date="24/09/2004" Time="7:30:24 PM" DateTime="2004-09-24T09:30:24.540Z" SessionID="7"><From><User FriendlyName="James*-)"/></From><To><User FriendlyName="erinleecarey@aol.com (E-mail Address Not Verified)"/></To><Text Style="font-family:Comic Sans MS; font-weight:bold; color:#000080; ">that incredinkalbe</Text></Message><Message Date="24/09/2004" Time="7:30:32 PM" DateTime="2004-09-24T09:30:32.301Z" SessionID="7"><From><User FriendlyName="James*-)"/></From><To><User FriendlyName="erinleecarey@aol.com (E-mail Address Not Verified)"/></To><Text Style="font-family:Comic Sans MS; font-weight:bold; color:#000080; ">No i like sumwun</Text></Message><Message Date="24/09/2004" Time="7:30:35 PM" DateTime="2004-09-24T09:30:35.075Z" SessionID="7"><From><User FriendlyName="James*-)"/></From><To><User FriendlyName="erinleecarey@aol.com (E-mail Address Not Verified)"/></To><Text Style="font-family:Comic Sans MS; font-weight:bold; color:#000080; ">I din even no that</Text></Message><Message Date="24/09/2004" Time="7:30:41 PM" DateTime="2004-09-24T09:30:41.034Z" SessionID="7"><From><User FriendlyName="James*-)"/></From><To><User FriendlyName="erinleecarey@aol.com (E-mail Address Not Verified)"/></To><Text Style="font-family:Comic Sans MS; font-weight:bold; color:#000080; "> :-O crrrraaaaaaaaaaaaaaaazy</Text></Message><Message Date="24/09/2004" Time="7:30:47 PM" DateTime="2004-09-24T09:30:47.012Z" SessionID="7"><From><User FriendlyName="erinleecarey@aol.com (E-mail Address Not Verified)"/></From><To><User FriendlyName="James*-)"/></To><Text Style="font-family:Papyrus; font-weight:bold; color:#ff00ff; ">um ok just answer the question funny boy</Text></Message><Message Date="24/09/2004" Time="7:31:21 PM" DateTime="2004-09-24T09:31:21.812Z" SessionID="7"><From><User FriendlyName="James*-)"/></From><To><User FriendlyName="erinleecarey@aol.com (E-mail Address Not Verified)"/></To><Text Style="font-family:Comic Sans MS; font-weight:bold; color:#000080; ">hehe I am funny, arent i :)</Text></Message><Message Date="24/09/2004" Time="7:32:04 PM" DateTime="2004-09-24T09:32:04.033Z" SessionID="7"><From><User FriendlyName="James*-)"/></From><To><User FriendlyName="erinleecarey@aol.com (E-mail Address Not Verified)"/></To><Text Style="font-family:Comic Sans MS; font-weight:bold; color:#000080; ">Yes thats right</Text></Message><Message Date="24/09/2004" Time="7:32:08 PM" DateTime="2004-09-24T09:32:08.870Z" SessionID="7"><From><User FriendlyName="James*-)"/></From><To><User FriendlyName="erinleecarey@aol.com (E-mail Address Not Verified)"/></To><Text Style="font-family:Comic Sans MS; font-weight:bold; color:#000080; ">Start typing and then stopp</Text></Message><Message Date="24/09/2004" Time="7:32:14 PM" DateTime="2004-09-24T09:32:14.829Z" SessionID="7"><From><User FriendlyName="James*-)"/></From><To><User FriendlyName="erinleecarey@aol.com (E-mail Address Not Verified)"/></To><Text Style="font-family:Comic Sans MS; font-weight:bold; color:#000080; ">I see thru ur petty ways</Text></Message><Message Date="24/09/2004" Time="7:32:30 PM" DateTime="2004-09-24T09:32:30.041Z" SessionID="7"><From><User FriendlyName="erinleecarey@aol.com (E-mail Address Not Verified)"/></From><To><User FriendlyName="James*-)"/></To><Text Style="font-family:Papyrus; font-weight:bold; color:#ff00ff; ">oh my god  i cant belive im sayin this but ur stupider that jess</Text></Message><Message Date="24/09/2004" Time="7:32:37 PM" DateTime="2004-09-24T09:32:37.652Z" SessionID="7"><From><User FriendlyName="James*-)"/></From><To><User FriendlyName="erinleecarey@aol.com (E-mail Address Not Verified)"/></To><Text Style="font-family:Comic Sans MS; font-weight:bold; color:#000080; ">:-O</Text></Message><Message Date="24/09/2004" Time="7:32:43 PM" DateTime="2004-09-24T09:32:43.520Z" SessionID="7"><From><User FriendlyName="James*-)"/></From><To><User FriendlyName="erinleecarey@aol.com (E-mail Address Not Verified)"/></To><Text Style="font-family:Comic Sans MS; font-weight:bold; color:#000080; ">u both shock and offend me</Text></Message><Message Date="24/09/2004" Time="7:32:52 PM" DateTime="2004-09-24T09:32:52.283Z" SessionID="7"><From><User FriendlyName="erinleecarey@aol.com (E-mail Address Not Verified)"/></From><To><User FriendlyName="James*-)"/></To><Text Style="font-family:Papyrus; font-weight:bold; color:#ff00ff; ">shutup i was talkin to sum 1 one else i do have other friends u know</Text></Message><Message Date="24/09/2004" Time="7:33:15 PM" DateTime="2004-09-24T09:33:15.185Z" SessionID="7"><From><User FriendlyName="James*-)"/></From><To><User FriendlyName="erinleecarey@aol.com (E-mail Address Not Verified)"/></To><Text Style="font-family:Comic Sans MS; font-weight:bold; color:#000080; ">ahhhh, wtf?</Text></Message><Message Date="24/09/2004" Time="7:33:26 PM" DateTime="2004-09-24T09:33:26.472Z" SessionID="7"><From><User FriendlyName="James*-)"/></From><To><User FriendlyName="erinleecarey@aol.com (E-mail Address Not Verified)"/></To><Text Style="font-family:Comic Sans MS; font-weight:bold; color:#000080; ">Wat</Text></Message><Message Date="24/09/2004" Time="7:33:33 PM" DateTime="2004-09-24T09:33:33.812Z" SessionID="7"><From><User FriendlyName="James*-)"/></From><To><User FriendlyName="erinleecarey@aol.com (E-mail Address Not Verified)"/></To><Text Style="font-family:Comic Sans MS; font-weight:bold; color:#000080; ">the hell r u on about?</Text></Message><Message Date="24/09/2004" Time="8:22:26 PM" DateTime="2004-09-24T10:22:26.059Z" SessionID="8"><From><User FriendlyName="James*-)"/></From><To><User FriendlyName="erinleecarey@aol.com (E-mail Address Not Verified)"/></To><Text Style="font-family:Comic Sans MS; font-weight:bold; color:#000080; ">Awo again</Text></Message><Message Date="3/11/2004" Time="8:33:52 PM" DateTime="2004-11-03T09:33:52.397Z" SessionID="9"><From><User FriendlyName="James*-) Pics or It didn't Happen..."/></From><To><User FriendlyName="erinleecarey@aol.com (E-mail Address Not Verified)"/></To><Text Style="font-family:Comic Sans MS; font-weight:bold; color:#000080; ">Find ur Ear-Ring?</Text></Message><Message Date="3/11/2004" Time="8:34:11 PM" DateTime="2004-11-03T09:34:11.754Z" SessionID="10"><From><User FriendlyName="erinleecarey@aol.com (E-mail Address Not Verified)"/></From><To><User FriendlyName="James*-) Pics or It didn't Happen..."/></To><Text Style="font-family:Papyrus; font-weight:bold; color:#ff00ff; ">nooooooo! :'(</Text></Message><Message Date="3/11/2004" Time="8:35:06 PM" DateTime="2004-11-03T09:35:06.553Z" SessionID="10"><From><User FriendlyName="James*-) Pics or It didn't Happen..."/></From><To><User FriendlyName="erinleecarey@aol.com (E-mail Address Not Verified)"/></To><Text Style="font-family:Comic Sans MS; font-weight:bold; color:#000080; ">ohh :( </Text></Message><Message Date="3/11/2004" Time="8:35:17 PM" DateTime="2004-11-03T09:35:17.789Z" SessionID="10"><From><User FriendlyName="James*-) Pics or It didn't Happen..."/></From><To><User FriendlyName="erinleecarey@aol.com (E-mail Address Not Verified)"/></To><Text Style="font-family:Comic Sans MS; font-weight:bold; color:#000080; ">Maybe u lost it when u threw damien down the hill ;)</Text></Message><Message Date="3/11/2004" Time="8:35:58 PM" DateTime="2004-11-03T09:35:58.238Z" SessionID="11"><From><User FriendlyName="erinleecarey@aol.com (E-mail Address Not Verified)"/></From><To><User FriendlyName="James*-) Pics or It didn't Happen..."/></To><Text Style="font-family:Papyrus; font-weight:bold; color:#ff00ff; ">nah that waz pretty funnire though - soz if i flashed u when i fell off sara</Text></Message><Message Date="3/11/2004" Time="8:36:51 PM" DateTime="2004-11-03T09:36:51.184Z" SessionID="11"><From><User FriendlyName="James*-) Pics or It didn't Happen..."/></From><To><User FriendlyName="erinleecarey@aol.com (E-mail Address Not Verified)"/></To><Text Style="font-family:Comic Sans MS; font-weight:bold; color:#000080; ">:-OU flashed me</Text></Message><Message Date="3/11/2004" Time="8:36:56 PM" DateTime="2004-11-03T09:36:56.802Z" SessionID="11"><From><User FriendlyName="James*-) Pics or It didn't Happen..."/></From><To><User FriendlyName="erinleecarey@aol.com (E-mail Address Not Verified)"/></To><Text Style="font-family:Comic Sans MS; font-weight:bold; color:#000080; ">:-O Andi didnt see</Text></Message><Message Date="3/11/2004" Time="8:37:02 PM" DateTime="2004-11-03T09:37:02.119Z" SessionID="11"><From><User FriendlyName="James*-) Pics or It didn't Happen..."/></From><To><User FriendlyName="erinleecarey@aol.com (E-mail Address Not Verified)"/></To><Text Style="font-family:Comic Sans MS; font-weight:bold; color:#000080; ">:(god i suc</Text></Message><Message Date="3/11/2004" Time="8:37:11 PM" DateTime="2004-11-03T09:37:11.633Z" SessionID="12"><From><User FriendlyName="erinleecarey@aol.com (E-mail Address Not Verified)"/></From><To><User FriendlyName="James*-) Pics or It didn't Happen..."/></To><Text Style="font-family:Papyrus; font-weight:bold; color:#ff00ff; ">lol!</Text></Message><Message Date="3/11/2004" Time="8:44:23 PM" DateTime="2004-11-03T09:44:23.574Z" SessionID="13"><From><User FriendlyName="erinleecarey@aol.com (E-mail Address Not Verified)"/></From><To><User FriendlyName="James*-) Pics or It didn't Happen..."/></To><Text Style="font-family:Papyrus; font-weight:bold; color:#ff00ff; ">so..........</Text></Message><Message Date="3/11/2004" Time="8:44:37 PM" DateTime="2004-11-03T09:44:37.714Z" SessionID="13"><From><User FriendlyName="James*-) Pics or It didn't Happen..."/></From><To><User FriendlyName="erinleecarey@aol.com (E-mail Address Not Verified)"/></To><Text Style="font-family:Comic Sans MS; font-weight:bold; color:#000080; ">yeah...........</Text></Message><Message Date="3/11/2004" Time="8:46:57 PM" DateTime="2004-11-03T09:46:57.065Z" SessionID="14"><From><User FriendlyName="erinleecarey@aol.com (E-mail Address Not Verified)"/></From><To><User FriendlyName="James*-) Pics or It didn't Happen..."/></To><Text Style="font-family:Papyrus; font-weight:bold; color:#ff00ff; ">wow this convo is like so deep</Text></Message><Message Date="3/11/2004" Time="8:47:03 PM" DateTime="2004-11-03T09:47:03.734Z" SessionID="14"><From><User FriendlyName="James*-) Pics or It didn't Happen..."/></From><To><User FriendlyName="erinleecarey@aol.com (E-mail Address Not Verified)"/></To><Text Style="font-family:Comic Sans MS; font-weight:bold; color:#000080; ">yeah</Text></Message><Message Date="3/11/2004" Time="8:47:07 PM" DateTime="2004-11-03T09:47:07.380Z" SessionID="14"><From><User FriendlyName="James*-) Pics or It didn't Happen..."/></From><To><User FriendlyName="erinleecarey@aol.com (E-mail Address Not Verified)"/></To><Text Style="font-family:Comic Sans MS; font-weight:bold; color:#000080; ">Im talking 2 beth</Text></Message><Message Date="3/11/2004" Time="8:47:07 PM" DateTime="2004-11-03T09:47:07.760Z" SessionID="14"><From><User FriendlyName="erinleecarey@aol.com (E-mail Address Not Verified)"/></From><To><User FriendlyName="James*-) Pics or It didn't Happen..."/></To><Text Style="font-family:Papyrus; font-weight:bold; color:#ff00ff; ">and filled with emotional conflict</Text></Message><Message Date="3/11/2004" Time="8:47:14 PM" DateTime="2004-11-03T09:47:14.921Z" SessionID="14"><From><User FriendlyName="James*-) Pics or It didn't Happen..."/></From><To><User FriendlyName="erinleecarey@aol.com (E-mail Address Not Verified)"/></To><Text Style="font-family:Comic Sans MS; font-weight:bold; color:#000080; ">and trying 2 get my fone thing 2 download</Text></Message><Message Date="3/11/2004" Time="8:47:25 PM" DateTime="2004-11-03T09:47:25.816Z" SessionID="14"><From><User FriendlyName="erinleecarey@aol.com (E-mail Address Not Verified)"/></From><To><User FriendlyName="James*-) Pics or It didn't Happen..."/></To><Text Style="font-family:Papyrus; font-weight:bold; color:#ff00ff; ">well then thats ok u little love birds</Text></Message><Message Date="3/11/2004" Time="8:48:04 PM" DateTime="2004-11-03T09:48:04.251Z" SessionID="14"><From><User FriendlyName="James*-) Pics or It didn't Happen..."/></From><To><User FriendlyName="erinleecarey@aol.com (E-mail Address Not Verified)"/></To><Text Style="font-family:Comic Sans MS; font-weight:bold; color:#000080; ">uhh</Text></Message><Message Date="3/11/2004" Time="8:48:11 PM" DateTime="2004-11-03T09:48:11.882Z" SessionID="14"><From><User FriendlyName="James*-) Pics or It didn't Happen..."/></From><To><User FriendlyName="erinleecarey@aol.com (E-mail Address Not Verified)"/></To><Text Style="font-family:Comic Sans MS; font-weight:bold; color:#000080; ">thanks i guess</Text></Message><Message Date="3/11/2004" Time="8:48:22 PM" DateTime="2004-11-03T09:48:22.928Z" SessionID="15"><From><User FriendlyName="erinleecarey@aol.com (E-mail Address Not Verified)"/></From><To><User FriendlyName="James*-) Pics or It didn't Happen..."/></To><Text Style="font-family:Papyrus; font-weight:bold; color:#ff00ff; ">:D</Text></Message><Message Date="3/11/2004" Time="8:55:09 PM" DateTime="2004-11-03T09:55:09.884Z" SessionID="16"><From><User FriendlyName="erinleecarey@aol.com (E-mail Address Not Verified)"/></From><To><User FriendlyName="James*-) Pics or It didn't Happen..."/></To><Text Style="font-family:Papyrus; font-weight:bold; color:#ff00ff; ">so do u like bethany</Text></Message><Message Date="3/11/2004" Time="8:58:25 PM" DateTime="2004-11-03T09:58:25.735Z" SessionID="17"><From><User FriendlyName="erinleecarey@aol.com (E-mail Address Not Verified)"/></From><To><User FriendlyName="James*-) Pics or It didn't Happen..."/></To><Text Style="font-family:Papyrus; font-weight:bold; color:#ff00ff; ">.........................?</Text></Message><Message Date="3/11/2004" Time="8:58:32 PM" DateTime="2004-11-03T09:58:32.635Z" SessionID="17"><From><User FriendlyName="James*-) Pics or It didn't Happen..."/></From><To><User FriendlyName="erinleecarey@aol.com (E-mail Address Not Verified)"/></To><Text Style="font-family:Comic Sans MS; font-weight:bold; color:#000080; ">,..............;)</Text></Message><Message Date="3/11/2004" Time="8:58:40 PM" DateTime="2004-11-03T09:58:40.807Z" SessionID="17"><From><User FriendlyName="James*-) Pics or It didn't Happen..."/></From><To><User FriendlyName="erinleecarey@aol.com (E-mail Address Not Verified)"/></To><Text Style="font-family:Comic Sans MS; font-weight:bold; color:#000080; ">wait that seems dodgy</Text></Message><Message Date="3/11/2004" Time="8:58:45 PM" DateTime="2004-11-03T09:58:45.594Z" SessionID="17"><From><User FriendlyName="James*-) Pics or It didn't Happen..."/></From><To><User FriendlyName="erinleecarey@aol.com (E-mail Address Not Verified)"/></To><Text Style="font-family:Comic Sans MS; font-weight:bold; color:#000080; ">No comment</Text></Message><Message Date="3/11/2004" Time="8:58:57 PM" DateTime="2004-11-03T09:58:57.240Z" SessionID="18"><From><User FriendlyName="erinleecarey@aol.com (E-mail Address Not Verified)"/></From><To><User FriendlyName="James*-) Pics or It didn't Happen..."/></To><Text Style="font-family:Papyrus; font-weight:bold; color:#ff00ff; ">y would it be dodgy?</Text></Message><Message Date="4/11/2004" Time="3:50:22 PM" DateTime="2004-11-04T04:50:22.615Z" SessionID="19"><From><User FriendlyName="erinleecarey@aol.com (E-mail Address Not Verified)"/></From><To><User FriendlyName="James*-) Pics or It didn't Happen..."/></To><Text Style="font-family:Papyrus; font-weight:bold; color:#ff00ff; ">hey j.n lova</Text></Message><Message Date="4/11/2004" Time="3:50:45 PM" DateTime="2004-11-04T04:50:45.197Z" SessionID="19"><From><User FriendlyName="erinleecarey@aol.com (E-mail Address Not Verified)"/></From><To><User FriendlyName="James*-) Pics or It didn't Happen..."/></To><Text Style="font-family:Papyrus; font-weight:bold; color:#ff00ff; ">..................</Text></Message><Message Date="4/11/2004" Time="3:51:10 PM" DateTime="2004-11-04T04:51:10.363Z" SessionID="19"><From><User FriendlyName="James*-) Pics or It didn't Happen..."/></From><To><User FriendlyName="erinleecarey@aol.com (E-mail Address Not Verified)"/></To><Text Style="font-family:Comic Sans MS; font-weight:bold; color:#000080; ">ermmmh</Text></Message><Message Date="4/11/2004" Time="3:51:13 PM" DateTime="2004-11-04T04:51:13.508Z" SessionID="19"><From><User FriendlyName="James*-) Pics or It didn't Happen..."/></From><To><User FriendlyName="erinleecarey@aol.com (E-mail Address Not Verified)"/></To><Text Style="font-family:Comic Sans MS; font-weight:bold; color:#000080; ">hello</Text></Message><Message Date="4/11/2004" Time="3:51:47 PM" DateTime="2004-11-04T04:51:47.146Z" SessionID="19"><From><User FriendlyName="James*-) Pics or It didn't Happen..."/></From><To><User FriendlyName="erinleecarey@aol.com (E-mail Address Not Verified)"/></To><Text Style="font-family:Comic Sans MS; font-weight:bold; color:#000080; ">ermmh wat r u incinuating with that lil "jn lova" comment</Text></Message><Message Date="4/11/2004" Time="3:52:36 PM" DateTime="2004-11-04T04:52:36.738Z" SessionID="19"><From><User FriendlyName="erinleecarey@aol.com (E-mail Address Not Verified)"/></From><To><User FriendlyName="James*-) Pics or It didn't Happen..."/></To><Text Style="font-family:Papyrus; font-weight:bold; color:#ff00ff; ">tha u like jess.......hello</Text></Message><Message Date="4/11/2004" Time="3:52:43 PM" DateTime="2004-11-04T04:52:43.127Z" SessionID="19"><From><User FriendlyName="James*-) Pics or It didn't Happen..."/></From><To><User FriendlyName="erinleecarey@aol.com (E-mail Address Not Verified)"/></To><Text Style="font-family:Comic Sans MS; font-weight:bold; color:#000080; ">:-O</Text></Message><Message Date="4/11/2004" Time="3:52:47 PM" DateTime="2004-11-04T04:52:47.163Z" SessionID="19"><From><User FriendlyName="James*-) Pics or It didn't Happen..."/></From><To><User FriendlyName="erinleecarey@aol.com (E-mail Address Not Verified)"/></To><Text Style="font-family:Comic Sans MS; font-weight:bold; color:#000080; ">Make up ur mind ffs</Text></Message><Message Date="4/11/2004" Time="3:52:48 PM" DateTime="2004-11-04T04:52:48.034Z" SessionID="19"><From><User FriendlyName="erinleecarey@aol.com (E-mail Address Not Verified)"/></From><To><User FriendlyName="James*-) Pics or It didn't Happen..."/></To><Text Style="font-family:Papyrus; font-weight:bold; color:#ff00ff; ">u still got glue in ur head or sumfin</Text></Message><Message Date="4/11/2004" Time="3:53:05 PM" DateTime="2004-11-04T04:53:05.489Z" SessionID="19"><From><User FriendlyName="James*-) Pics or It didn't Happen..."/></From><To><User FriendlyName="erinleecarey@aol.com (E-mail Address Not Verified)"/></To><Text Style="font-family:Comic Sans MS; font-weight:bold; color:#000080; ">I thought i liked beth half an hour ago:S</Text></Message><Message Date="4/11/2004" Time="3:53:11 PM" DateTime="2004-11-04T04:53:11.357Z" SessionID="19"><From><User FriendlyName="James*-) Pics or It didn't Happen..."/></From><To><User FriendlyName="erinleecarey@aol.com (E-mail Address Not Verified)"/></To><Text Style="font-family:Comic Sans MS; font-weight:bold; color:#000080; ">oh well, what do i now?</Text></Message><Message Date="4/11/2004" Time="3:53:53 PM" DateTime="2004-11-04T04:53:53.728Z" SessionID="20"><From><User FriendlyName="erinleecarey@aol.com (E-mail Address Not Verified)"/></From><To><User FriendlyName="James*-) Pics or It didn't Happen..."/></To><Text Style="font-family:Papyrus; font-weight:bold; color:#ff00ff; ">yeah well thats before i saw that little convorsation u gona ask out jess</Text></Message><Message Date="4/11/2004" Time="3:54:11 PM" DateTime="2004-11-04T04:54:11.314Z" SessionID="20"><From><User FriendlyName="erinleecarey@aol.com (E-mail Address Not Verified)"/></From><To><User FriendlyName="James*-) Pics or It didn't Happen..."/></To><Text Style="font-family:Papyrus; font-weight:bold; color:#ff00ff; ">...................</Text></Message><Message Date="4/11/2004" Time="3:54:16 PM" DateTime="2004-11-04T04:54:16.060Z" SessionID="20"><From><User FriendlyName="erinleecarey@aol.com (E-mail Address Not Verified)"/></From><To><User FriendlyName="James*-) Pics or It didn't Happen..."/></To><Text Style="font-family:Papyrus; font-weight:bold; color:#ff00ff; ">pleeeeeeeeeeeeeeez</Text></Message><Message Date="4/11/2004" Time="3:54:51 PM" DateTime="2004-11-04T04:54:51.972Z" SessionID="20"><From><User FriendlyName="erinleecarey@aol.com (E-mail Address Not Verified)"/></From><To><User FriendlyName="James*-) Pics or It didn't Happen..."/></To><Text Style="font-family:Papyrus; font-weight:bold; color:#ff00ff; ">.........................</Text></Message><Message Date="4/11/2004" Time="3:55:54 PM" DateTime="2004-11-04T04:55:54.212Z" SessionID="20"><From><User FriendlyName="erinleecarey@aol.com (E-mail Address Not Verified)"/></From><To><User FriendlyName="James*-) Pics or It didn't Happen..."/></To><Text Style="font-family:Papyrus; font-weight:bold; color:#ff00ff; ">fine then go have no fun sumwhere else</Text></Message><Message Date="4/11/2004" Time="3:56:13 PM" DateTime="2004-11-04T04:56:13.219Z" SessionID="20"><From><User FriendlyName="James*-) Pics or It didn't Happen..."/></From><To><User FriendlyName="erinleecarey@aol.com (E-mail Address Not Verified)"/></To><Text Style="font-family:Comic Sans MS; font-weight:bold; color:#000080; ">^o)</Text></Message><Message Date="4/11/2004" Time="3:56:20 PM" DateTime="2004-11-04T04:56:20.519Z" SessionID="20"><From><User FriendlyName="James*-) Pics or It didn't Happen..."/></From><To><User FriendlyName="erinleecarey@aol.com (E-mail Address Not Verified)"/></To><Text Style="font-family:Comic Sans MS; font-weight:bold; color:#000080; ">what conversation!</Text></Message><Message Date="4/11/2004" Time="3:56:31 PM" DateTime="2004-11-04T04:56:31.495Z" SessionID="20"><From><User FriendlyName="James*-) Pics or It didn't Happen..."/></From><To><User FriendlyName="erinleecarey@aol.com (E-mail Address Not Verified)"/></To><Text Style="font-family:Comic Sans MS; font-weight:bold; color:#000080; ">Show us</Text></Message><Message Date="4/11/2004" Time="3:57:04 PM" DateTime="2004-11-04T04:57:04.222Z" SessionID="20"><From><User FriendlyName="erinleecarey@aol.com (E-mail Address Not Verified)"/></From><To><User FriendlyName="James*-) Pics or It didn't Happen..."/></To><Text Style="font-family:Papyrus; font-weight:bold; color:#ff00ff; ">um i duno it went like this, will u go out wiv jess, yes</Text></Message><Message Date="4/11/2004" Time="3:57:18 PM" DateTime="2004-11-04T04:57:18.433Z" SessionID="20"><From><User FriendlyName="erinleecarey@aol.com (E-mail Address Not Verified)"/></From><To><User FriendlyName="James*-) Pics or It didn't Happen..."/></To><Text Style="font-family:Papyrus; font-weight:bold; color:#ff00ff; ">i dont have it u knong</Text></Message><Message Date="4/11/2004" Time="3:57:50 PM" DateTime="2004-11-04T04:57:50.729Z" SessionID="20"><From><User FriendlyName="James*-) Pics or It didn't Happen..."/></From><To><User FriendlyName="erinleecarey@aol.com (E-mail Address Not Verified)"/></To><Text Style="font-family:Comic Sans MS; font-weight:bold; color:#000080; ">Wtf u on abot</Text></Message><Message Date="4/11/2004" Time="3:58:10 PM" DateTime="2004-11-04T04:58:10.808Z" SessionID="20"><From><User FriendlyName="James*-) Pics or It didn't Happen..."/></From><To><User FriendlyName="erinleecarey@aol.com (E-mail Address Not Verified)"/></To><Text Style="font-family:Comic Sans MS; font-weight:bold; color:#000080; ">i thought u were talkin bout a nuth conversation between me n beth</Text></Message><Message Date="4/11/2004" Time="3:58:13 PM" DateTime="2004-11-04T04:58:13.161Z" SessionID="20"><From><User FriendlyName="erinleecarey@aol.com (E-mail Address Not Verified)"/></From><To><User FriendlyName="James*-) Pics or It didn't Happen..."/></To><Text Style="font-family:Papyrus; font-weight:bold; color:#ff00ff; ">i think u know</Text></Message><Message Date="4/11/2004" Time="3:58:25 PM" DateTime="2004-11-04T04:58:25.860Z" SessionID="20"><From><User FriendlyName="James*-) Pics or It didn't Happen..."/></From><To><User FriendlyName="erinleecarey@aol.com (E-mail Address Not Verified)"/></To><Text Style="font-family:Comic Sans MS; font-weight:bold; color:#000080; ">ermmh no</Text></Message><Message Date="4/11/2004" Time="3:58:29 PM" DateTime="2004-11-04T04:58:29.535Z" SessionID="20"><From><User FriendlyName="erinleecarey@aol.com (E-mail Address Not Verified)"/></From><To><User FriendlyName="James*-) Pics or It didn't Happen..."/></To><Text Style="font-family:Papyrus; font-weight:bold; color:#ff00ff; ">just tell me do u like jess or not</Text></Message><Message Date="4/11/2004" Time="3:58:38 PM" DateTime="2004-11-04T04:58:38.608Z" SessionID="20"><From><User FriendlyName="James*-) Pics or It didn't Happen..."/></From><To><User FriendlyName="erinleecarey@aol.com (E-mail Address Not Verified)"/></To><Text Style="font-family:Comic Sans MS; font-weight:bold; color:#000080; ">WTF U ON ABOUT!</Text></Message><Message Date="4/11/2004" Time="3:58:52 PM" DateTime="2004-11-04T04:58:52.838Z" SessionID="20"><From><User FriendlyName="erinleecarey@aol.com (E-mail Address Not Verified)"/></From><To><User FriendlyName="James*-) Pics or It didn't Happen..."/></To><Text Style="font-family:Papyrus; font-weight:bold; color:#ff00ff; ">do u like jess newy</Text></Message><Message Date="4/11/2004" Time="3:59:05 PM" DateTime="2004-11-04T04:59:05.527Z" SessionID="20"><From><User FriendlyName="James*-) Pics or It didn't Happen..."/></From><To><User FriendlyName="erinleecarey@aol.com (E-mail Address Not Verified)"/></To><Text Style="font-family:Comic Sans MS; font-weight:bold; color:#000080; ">NO</Text></Message><Message Date="4/11/2004" Time="3:59:13 PM" DateTime="2004-11-04T04:59:13.027Z" SessionID="20"><From><User FriendlyName="James*-) Pics or It didn't Happen..."/></From><To><User FriendlyName="erinleecarey@aol.com (E-mail Address Not Verified)"/></To><Text Style="font-family:Comic Sans MS; font-weight:bold; color:#000080; ">but why what conversation!</Text></Message><Message Date="4/11/2004" Time="3:59:31 PM" DateTime="2004-11-04T04:59:31.274Z" SessionID="21"><From><User FriendlyName="erinleecarey@aol.com (E-mail Address Not Verified)"/></From><To><User FriendlyName="James*-) Pics or It didn't Happen..."/></To><Text Style="font-family:Papyrus; font-weight:bold; color:#ff00ff; ">well do u like bethany</Text></Message><Message Date="4/11/2004" Time="3:59:55 PM" DateTime="2004-11-04T04:59:55.098Z" SessionID="21"><From><User FriendlyName="erinleecarey@aol.com (E-mail Address Not Verified)"/></From><To><User FriendlyName="James*-) Pics or It didn't Happen..."/></To><Text Style="font-family:Papyrus; font-weight:bold; color:#ff00ff; ">i take that as a yes</Text></Message><Message Date="4/11/2004" Time="4:00:02 PM" DateTime="2004-11-04T05:00:02.939Z" SessionID="21"><From><User FriendlyName="erinleecarey@aol.com (E-mail Address Not Verified)"/></From><To><User FriendlyName="James*-) Pics or It didn't Happen..."/></To><Text Style="font-family:Papyrus; font-weight:bold; color:#ff00ff; ">awww thats so cute</Text></Message><Message Date="4/11/2004" Time="4:01:01 PM" DateTime="2004-11-04T05:01:01.253Z" SessionID="21"><From><User FriendlyName="erinleecarey@aol.com (E-mail Address Not Verified)"/></From><To><User FriendlyName="James*-) Pics or It didn't Happen..."/></To><Text Style="font-family:Papyrus; font-weight:bold; color:#ff00ff; ">gtg cya</Text></Message><Message Date="4/11/2004" Time="4:01:31 PM" DateTime="2004-11-04T05:01:31.497Z" SessionID="21"><From><User FriendlyName="James*-) Pics or It didn't Happen..."/></From><To><User FriendlyName="erinleecarey@aol.com (E-mail Address Not Verified)"/></To><Text Style="font-family:Comic Sans MS; font-weight:bold; color:#000080; ">ermmh</Text></Message><Message Date="4/11/2004" Time="4:01:38 PM" DateTime="2004-11-04T05:01:38.717Z" SessionID="21"><From><User FriendlyName="James*-) Pics or It didn't Happen..."/></From><To><User FriendlyName="erinleecarey@aol.com (E-mail Address Not Verified)"/></To><Text Style="font-family:Comic Sans MS; font-weight:bold; color:#000080; ">ok mis lil i wont xplaing anything</Text></Message><Message Date="4/11/2004" Time="4:01:50 PM" DateTime="2004-11-04T05:01:50.824Z" SessionID="21"><From><User FriendlyName="James*-) Pics or It didn't Happen..."/></From><To><User FriendlyName="erinleecarey@aol.com (E-mail Address Not Verified)"/></To><Text Style="font-family:Comic Sans MS; font-weight:bold; color:#000080; ">WHAT CONVERSATION IS IT!</Text></Message><Message Date="4/11/2004" Time="4:02:04 PM" DateTime="2004-11-04T05:02:04.584Z" SessionID="21"><From><User FriendlyName="James*-) Pics or It didn't Happen..."/></From><To><User FriendlyName="erinleecarey@aol.com (E-mail Address Not Verified)"/></To><Text Style="font-family:Comic Sans MS; font-weight:bold; color:#000080; ">...</Text></Message><Message Date="4/11/2004" Time="4:02:05 PM" DateTime="2004-11-04T05:02:05.185Z" SessionID="21"><From><User FriendlyName="James*-) Pics or It didn't Happen..."/></From><To><User FriendlyName="erinleecarey@aol.com (E-mail Address Not Verified)"/></To><Text Style="font-family:Comic Sans MS; font-weight:bold; color:#000080; ">...</Text></Message><Message Date="4/11/2004" Time="4:02:53 PM" DateTime="2004-11-04T05:02:53.675Z" SessionID="21"><From><User FriendlyName="James*-) Pics or Your a 50 year old bald biker..."/></From><To><User FriendlyName="erinleecarey@aol.com (E-mail Address Not Verified)"/></To><Text Style="font-family:Comic Sans MS; font-weight:bold; color:#000080; ">OMG</Text></Message><Message Date="4/11/2004" Time="4:03:09 PM" DateTime="2004-11-04T05:03:09.307Z" SessionID="21"><From><User FriendlyName="James*-) Pics or Your a 50 year old bald biker..."/></From><To><User FriendlyName="erinleecarey@aol.com (E-mail Address Not Verified)"/></To><Text Style="font-family:Comic Sans MS; font-weight:bold; color:#000080; ">What conversation did i say i like jess?</Text></Message><Message Date="5/11/2004" Time="7:39:27 PM" DateTime="2004-11-05T08:39:27.577Z" SessionID="22"><From><User FriendlyName="erinleecarey@aol.com (E-mail Address Not Verified)"/></From><To><User FriendlyName="James*-) I think therefore I am... I think."/></To><Text Style="font-family:MS Sans Serif; color:#000000; ">hey</Text></Message><Message Date="5/11/2004" Time="7:39:39 PM" DateTime="2004-11-05T08:39:39.555Z" SessionID="22"><From><User FriendlyName="James*-) I think therefore I am... I think."/></From><To><User FriendlyName="erinleecarey@aol.com (E-mail Address Not Verified)"/></To><Text Style="font-family:Comic Sans MS; font-weight:bold; color:#000080; ">How :)</Text></Message><Message Date="5/11/2004" Time="7:40:15 PM" DateTime="2004-11-05T08:40:15.256Z" SessionID="22"><From><User FriendlyName="erinleecarey@aol.com (E-mail Address Not Verified)"/></From><To><User FriendlyName="James*-) I think therefore I am... I think."/></To><Text Style="font-family:MS Sans Serif; color:#000000; ">how............ goin for the whole indian thing........nice</Text></Message><Message Date="5/11/2004" Time="7:40:51 PM" DateTime="2004-11-05T08:40:51.969Z" SessionID="22"><From><User FriendlyName="James*-) I think therefore I am... I think."/></From><To><User FriendlyName="erinleecarey@aol.com (E-mail Address Not Verified)"/></To><Text Style="font-family:Comic Sans MS; font-weight:bold; color:#000080; ">Yarhgen (thats swedish or sumfin</Text></Message><Message Date="5/11/2004" Time="7:41:21 PM" DateTime="2004-11-05T08:41:21.051Z" SessionID="23"><From><User FriendlyName="erinleecarey@aol.com (E-mail Address Not Verified)"/></From><To><User FriendlyName="James*-) I think therefore I am... I think."/></To><Text Style="font-family:MS Sans Serif; color:#000000; ">hagen daze</Text></Message><Message Date="5/11/2004" Time="7:41:29 PM" DateTime="2004-11-05T08:41:29.983Z" SessionID="23"><From><User FriendlyName="erinleecarey@aol.com (E-mail Address Not Verified)"/></From><To><User FriendlyName="James*-) I think therefore I am... I think."/></To><Text Style="font-family:MS Sans Serif; color:#000000; ">heheh thats an icecream</Text></Message><Message Date="5/11/2004" Time="7:42:14 PM" DateTime="2004-11-05T08:42:14.768Z" SessionID="23"><From><User FriendlyName="James*-) I think therefore I am... I think."/></From><To><User FriendlyName="erinleecarey@aol.com (E-mail Address Not Verified)"/></To><Text Style="font-family:Comic Sans MS; font-weight:bold; color:#000080; ">MMMH :)</Text></Message><Message Date="5/11/2004" Time="7:42:16 PM" DateTime="2004-11-05T08:42:16.741Z" SessionID="23"><From><User FriendlyName="James*-) I think therefore I am... I think."/></From><To><User FriendlyName="erinleecarey@aol.com (E-mail Address Not Verified)"/></To><Text Style="font-family:Comic Sans MS; font-weight:bold; color:#000080; ">Ice Cream</Text></Message><Message Date="5/11/2004" Time="7:42:45 PM" DateTime="2004-11-05T08:42:45.792Z" SessionID="23"><From><User FriendlyName="James*-) I think therefore I am... I think."/></From><To><User FriendlyName="erinleecarey@aol.com (E-mail Address Not Verified)"/></To><Text Style="font-family:Comic Sans MS; font-weight:bold; color:#000080; ">:D</Text></Message><Message Date="5/11/2004" Time="7:42:57 PM" DateTime="2004-11-05T08:42:57.369Z" SessionID="23"><From><User FriendlyName="James*-) I think therefore I am... I think."/></From><To><User FriendlyName="erinleecarey@aol.com (E-mail Address Not Verified)"/></To><Text Style="font-family:Comic Sans MS; font-weight:bold; color:#000080; ">soooooooo..</Text></Message><Message Date="5/11/2004" Time="7:42:59 PM" DateTime="2004-11-05T08:42:59.883Z" SessionID="23"><From><User FriendlyName="James*-) I think therefore I am... I think."/></From><To><User FriendlyName="erinleecarey@aol.com (E-mail Address Not Verified)"/></To><Text Style="font-family:Comic Sans MS; font-weight:bold; color:#000080; ">How u doin ;)</Text></Message><Message Date="5/11/2004" Time="7:43:08 PM" DateTime="2004-11-05T08:43:08.645Z" SessionID="23"><From><User FriendlyName="James*-) I think therefore I am... I think."/></From><To><User FriendlyName="erinleecarey@aol.com (E-mail Address Not Verified)"/></To><Text Style="font-family:Comic Sans MS; font-weight:bold; color:#000080; ">(in the none sleezy pick up line way)</Text></Message><Message Date="5/11/2004" Time="7:43:14 PM" DateTime="2004-11-05T08:43:14.163Z" SessionID="23"><From><User FriendlyName="James*-) I think therefore I am... I think."/></From><To><User FriendlyName="erinleecarey@aol.com (E-mail Address Not Verified)"/></To><Text Style="font-family:Comic Sans MS; font-weight:bold; color:#000080; ">:)</Text></Message><Message Date="5/11/2004" Time="7:45:34 PM" DateTime="2004-11-05T08:45:34.595Z" SessionID="24"><From><User FriendlyName="erinleecarey@aol.com (E-mail Address Not Verified)"/></From><To><User FriendlyName="James*-) I think therefore I am... I think."/></To><Text Style="font-family:MS Sans Serif; color:#000000; ">oh sure</Text></Message><Message Date="5/11/2004" Time="7:45:41 PM" DateTime="2004-11-05T08:45:41.545Z" SessionID="24"><From><User FriendlyName="James*-) I think therefore I am... I think."/></From><To><User FriendlyName="erinleecarey@aol.com (E-mail Address Not Verified)"/></To><Text Style="font-family:Comic Sans MS; font-weight:bold; color:#000080; ">:D</Text></Message><Message Date="5/11/2004" Time="7:45:43 PM" DateTime="2004-11-05T08:45:43.898Z" SessionID="24"><From><User FriendlyName="erinleecarey@aol.com (E-mail Address Not Verified)"/></From><To><User FriendlyName="James*-) I think therefore I am... I think."/></To><Text Style="font-family:MS Sans Serif; color:#000000; ">r u gonna ask out beth</Text></Message><Message Date="5/11/2004" Time="7:46:30 PM" DateTime="2004-11-05T08:46:30.425Z" SessionID="24"><From><User FriendlyName="James*-) I think therefore I am... I think."/></From><To><User FriendlyName="erinleecarey@aol.com (E-mail Address Not Verified)"/></To><Text Style="font-family:Comic Sans MS; font-weight:bold; color:#000080; ">neg</Text></Message><Message Date="5/11/2004" Time="7:47:45 PM" DateTime="2004-11-05T08:47:45.904Z" SessionID="25"><From><User FriendlyName="erinleecarey@aol.com (E-mail Address Not Verified)"/></From><To><User FriendlyName="James*-) I think therefore I am... I think."/></To><Text Style="font-family:MS Sans Serif; color:#000000; ">omg u r an idiot i mean u both like each other, just ask her out</Text></Message><Message Date="5/11/2004" Time="7:51:28 PM" DateTime="2004-11-05T08:51:28.925Z" SessionID="25"><From><User FriendlyName="James*-) I think therefore I am... I think."/></From><To><User FriendlyName="erinleecarey@aol.com (E-mail Address Not Verified)"/></To><Text Style="font-family:Comic Sans MS; font-weight:bold; color:#000080; ">Well im no idot ;)</Text></Message><Message Date="5/11/2004" Time="7:51:28 PM" DateTime="2004-11-05T08:51:28.995Z" SessionID="25"><From><User FriendlyName="erinleecarey@aol.com (E-mail Address Not Verified)"/></From><To><User FriendlyName="James*-) I think therefore I am... I think."/></To><Text Style="font-family:MS Sans Serif; color:#000000; ">........................? </Text></Message><Message Date="5/11/2004" Time="7:51:34 PM" DateTime="2004-11-05T08:51:34.062Z" SessionID="25"><From><User FriendlyName="erinleecarey@aol.com (E-mail Address Not Verified)"/></From><To><User FriendlyName="James*-) I think therefore I am... I think."/></To><Text Style="font-family:MS Sans Serif; color:#000000; ">watever</Text></Message><Message Date="5/11/2004" Time="7:51:35 PM" DateTime="2004-11-05T08:51:35.374Z" SessionID="25"><From><User FriendlyName="James*-) I think therefore I am... I think."/></From><To><User FriendlyName="erinleecarey@aol.com (E-mail Address Not Verified)"/></To><Text Style="font-family:Comic Sans MS; font-weight:bold; color:#000080; ">(hahaha, yeah right)</Text></Message><Message Date="5/11/2004" Time="7:51:50 PM" DateTime="2004-11-05T08:51:50.666Z" SessionID="26"><From><User FriendlyName="James*-) I think therefore I am... I think."/></From><To><User FriendlyName="erinleecarey@aol.com (E-mail Address Not Verified)"/></To><Text Style="font-family:Comic Sans MS; font-weight:bold; color:#000080; ">ermmh</Text></Message><Message Date="5/11/2004" Time="7:51:55 PM" DateTime="2004-11-05T08:51:55.323Z" SessionID="26"><From><User FriendlyName="James*-) I think therefore I am... I think."/></From><To><User FriendlyName="erinleecarey@aol.com (E-mail Address Not Verified)"/></To><Text Style="font-family:Comic Sans MS; font-weight:bold; color:#000080; ">Duz it really matter 2 u&gt;</Text></Message><Message Date="5/11/2004" Time="7:52:32 PM" DateTime="2004-11-05T08:52:32.316Z" SessionID="27"><From><User FriendlyName="erinleecarey@aol.com (E-mail Address Not Verified)"/></From><To><User FriendlyName="James*-) I think therefore I am... I think."/></To><Text Style="font-family:MS Sans Serif; color:#000000; ">yes cause shes a really good friend of mine and if u hurt her in any way u gona reget it</Text></Message><Message Date="5/11/2004" Time="7:53:41 PM" DateTime="2004-11-05T08:53:41.075Z" SessionID="27"><From><User FriendlyName="James*-) I think therefore I am... I think."/></From><To><User FriendlyName="erinleecarey@aol.com (E-mail Address Not Verified)"/></To><Text Style="font-family:Comic Sans MS; font-weight:bold; color:#000080; ">what ull gluee my hair and right on my arm?</Text></Message><Message Date="5/11/2004" Time="7:53:46 PM" DateTime="2004-11-05T08:53:46.442Z" SessionID="27"><From><User FriendlyName="James*-) I think therefore I am... I think."/></From><To><User FriendlyName="erinleecarey@aol.com (E-mail Address Not Verified)"/></To><Text Style="font-family:Comic Sans MS; font-weight:bold; color:#000080; ">:P</Text></Message><Message Date="5/11/2004" Time="7:53:52 PM" DateTime="2004-11-05T08:53:52.481Z" SessionID="27"><From><User FriendlyName="James*-) I think therefore I am... I think."/></From><To><User FriendlyName="erinleecarey@aol.com (E-mail Address Not Verified)"/></To><Text Style="font-family:Comic Sans MS; font-weight:bold; color:#000080; ">no im not</Text></Message><Message Date="5/11/2004" Time="7:54:25 PM" DateTime="2004-11-05T08:54:25.008Z" SessionID="28"><From><User FriendlyName="erinleecarey@aol.com (E-mail Address Not Verified)"/></From><To><User FriendlyName="James*-) I think therefore I am... I think."/></To><Text Style="font-family:MS Sans Serif; color:#000000; ">thats just my warm up act - il make ur life a livin hell </Text></Message><Message Date="5/11/2004" Time="7:54:44 PM" DateTime="2004-11-05T08:54:44.205Z" SessionID="28"><From><User FriendlyName="erinleecarey@aol.com (E-mail Address Not Verified)"/></From><To><User FriendlyName="James*-) I think therefore I am... I think."/></To><Text Style="font-family:MS Sans Serif; color:#000000; ">so u gona ask her out :)</Text></Message><Message Date="5/11/2004" Time="7:54:56 PM" DateTime="2004-11-05T08:54:56.753Z" SessionID="28"><From><User FriendlyName="James*-) I think therefore I am... I think."/></From><To><User FriendlyName="erinleecarey@aol.com (E-mail Address Not Verified)"/></To><Text Style="font-family:Comic Sans MS; font-weight:bold; color:#000080; ">8-) Stop trying 2 sound tough!</Text></Message><Message Date="5/11/2004" Time="7:56:26 PM" DateTime="2004-11-05T08:56:26.743Z" SessionID="28"><From><User FriendlyName="erinleecarey@aol.com (E-mail Address Not Verified)"/></From><To><User FriendlyName="James*-) I think therefore I am... I think."/></To><Text Style="font-family:MS Sans Serif; color:#000000; ">u dont fink im tough</Text></Message><Message Date="5/11/2004" Time="7:56:45 PM" DateTime="2004-11-05T08:56:45.640Z" SessionID="28"><From><User FriendlyName="James*-) I think therefore I am... I think."/></From><To><User FriendlyName="erinleecarey@aol.com (E-mail Address Not Verified)"/></To><Text Style="font-family:Comic Sans MS; font-weight:bold; color:#000080; ">ERmmh</Text></Message><Message Date="5/11/2004" Time="7:56:46 PM" DateTime="2004-11-05T08:56:46.241Z" SessionID="28"><From><User FriendlyName="James*-) I think therefore I am... I think."/></From><To><User FriendlyName="erinleecarey@aol.com (E-mail Address Not Verified)"/></To><Text Style="font-family:Comic Sans MS; font-weight:bold; color:#000080; ">no</Text></Message><Message Date="5/11/2004" Time="7:56:57 PM" DateTime="2004-11-05T08:56:57.617Z" SessionID="28"><From><User FriendlyName="James*-) I think therefore I am... I think."/></From><To><User FriendlyName="erinleecarey@aol.com (E-mail Address Not Verified)"/></To><Text Style="font-family:Comic Sans MS; font-weight:bold; color:#000080; ">look i have no intentions of hurting beth</Text></Message><Message Date="5/11/2004" Time="7:57:34 PM" DateTime="2004-11-05T08:57:34.320Z" SessionID="28"><From><User FriendlyName="James*-) I think therefore I am... I think."/></From><To><User FriendlyName="erinleecarey@aol.com (E-mail Address Not Verified)"/></To><Text Style="font-family:Comic Sans MS; font-weight:bold; color:#000080; ">So dont start threats cuz im a stupid panzy and nuthins gonner happen mmk</Text></Message><Message Date="5/11/2004" Time="7:57:39 PM" DateTime="2004-11-05T08:57:39.427Z" SessionID="29"><From><User FriendlyName="erinleecarey@aol.com (E-mail Address Not Verified)"/></From><To><User FriendlyName="James*-) I think therefore I am... I think."/></To><Text Style="font-family:MS Sans Serif; color:#000000; ">u may not have the intentions, but u mite.........guys are idiots when i comes to theses things</Text></Message><Message Date="5/11/2004" Time="7:57:46 PM" DateTime="2004-11-05T08:57:46.387Z" SessionID="29"><From><User FriendlyName="erinleecarey@aol.com (E-mail Address Not Verified)"/></From><To><User FriendlyName="James*-) I think therefore I am... I think."/></To><Text Style="font-family:MS Sans Serif; color:#000000; ">goodo</Text></Message><Message Date="5/11/2004" Time="7:57:51 PM" DateTime="2004-11-05T08:57:51.194Z" SessionID="29"><From><User FriendlyName="James*-) I think therefore I am... I think."/></From><To><User FriendlyName="erinleecarey@aol.com (E-mail Address Not Verified)"/></To><Text Style="font-family:Comic Sans MS; font-weight:bold; color:#000080; ">Good</Text></Message><Message Date="5/11/2004" Time="7:57:53 PM" DateTime="2004-11-05T08:57:53.387Z" SessionID="29"><From><User FriendlyName="James*-) I think therefore I am... I think."/></From><To><User FriendlyName="erinleecarey@aol.com (E-mail Address Not Verified)"/></To><Text Style="font-family:Comic Sans MS; font-weight:bold; color:#000080; ">ermmh</Text></Message><Message Date="5/11/2004" Time="7:58:04 PM" DateTime="2004-11-05T08:58:04.584Z" SessionID="29"><From><User FriendlyName="James*-) I think therefore I am... I think."/></From><To><User FriendlyName="erinleecarey@aol.com (E-mail Address Not Verified)"/></To><Text Style="font-family:Comic Sans MS; font-weight:bold; color:#000080; ">u just realised i sed nuthings gonenr happen n u sed good</Text></Message><Message Date="5/11/2004" Time="7:58:07 PM" DateTime="2004-11-05T08:58:07.277Z" SessionID="29"><From><User FriendlyName="James*-) I think therefore I am... I think."/></From><To><User FriendlyName="erinleecarey@aol.com (E-mail Address Not Verified)"/></To><Text Style="font-family:Comic Sans MS; font-weight:bold; color:#000080; ">ok just checking</Text></Message><Message Date="5/11/2004" Time="7:58:23 PM" DateTime="2004-11-05T08:58:23.330Z" SessionID="30"><From><User FriendlyName="erinleecarey@aol.com (E-mail Address Not Verified)"/></From><To><User FriendlyName="James*-) I think therefore I am... I think."/></To><Text Style="font-family:MS Sans Serif; color:#000000; ">fuk stop confusin me</Text></Message><Message Date="5/11/2004" Time="7:58:36 PM" DateTime="2004-11-05T08:58:36.519Z" SessionID="30"><From><User FriendlyName="erinleecarey@aol.com (E-mail Address Not Verified)"/></From><To><User FriendlyName="James*-) I think therefore I am... I think."/></To><Text Style="font-family:MS Sans Serif; color:#000000; ">:@ its reallay anoyin</Text></Message><Message Date="5/11/2004" Time="7:58:53 PM" DateTime="2004-11-05T08:58:53.744Z" SessionID="30"><From><User FriendlyName="James*-) I think therefore I am... I think."/></From><To><User FriendlyName="erinleecarey@aol.com (E-mail Address Not Verified)"/></To><Text Style="font-family:Comic Sans MS; font-weight:bold; color:#000080; ">Yeah thats wat she used 2 always say</Text></Message><Message Date="5/11/2004" Time="7:59:58 PM" DateTime="2004-11-05T08:59:58.417Z" SessionID="31"><From><User FriendlyName="erinleecarey@aol.com (E-mail Address Not Verified)"/></From><To><User FriendlyName="James*-) I think therefore I am... I think."/></To><Text Style="font-family:MS Sans Serif; color:#000000; ">who?</Text></Message><Message Date="5/11/2004" Time="8:00:59 PM" DateTime="2004-11-05T09:00:59.795Z" SessionID="31"><From><User FriendlyName="James*-) I think therefore I am... I think."/></From><To><User FriendlyName="erinleecarey@aol.com (E-mail Address Not Verified)"/></To><Text Style="font-family:Comic Sans MS; font-weight:bold; color:#000080; ">lol</Text></Message><Message Date="5/11/2004" Time="8:01:03 PM" DateTime="2004-11-05T09:01:03.431Z" SessionID="31"><From><User FriendlyName="James*-) I think therefore I am... I think."/></From><To><User FriendlyName="erinleecarey@aol.com (E-mail Address Not Verified)"/></To><Text Style="font-family:Comic Sans MS; font-weight:bold; color:#000080; ">fuk it</Text></Message><Message Date="5/11/2004" Time="8:01:09 PM" DateTime="2004-11-05T09:01:09.770Z" SessionID="31"><From><User FriendlyName="James*-) I think therefore I am... I think."/></From><To><User FriendlyName="erinleecarey@aol.com (E-mail Address Not Verified)"/></To><Text Style="font-family:Comic Sans MS; font-weight:bold; color:#000080; ">no seriously</Text></Message><Message Date="5/11/2004" Time="8:01:13 PM" DateTime="2004-11-05T09:01:13.115Z" SessionID="31"><From><User FriendlyName="James*-) I think therefore I am... I think."/></From><To><User FriendlyName="erinleecarey@aol.com (E-mail Address Not Verified)"/></To><Text Style="font-family:Comic Sans MS; font-weight:bold; color:#000080; ">just drop it</Text></Message><Message Date="5/11/2004" Time="8:01:14 PM" DateTime="2004-11-05T09:01:14.336Z" SessionID="31"><From><User FriendlyName="James*-) I think therefore I am... I think."/></From><To><User FriendlyName="erinleecarey@aol.com (E-mail Address Not Verified)"/></To><Text Style="font-family:Comic Sans MS; font-weight:bold; color:#000080; ">mmk</Text></Message><Message Date="5/11/2004" Time="8:01:58 PM" DateTime="2004-11-05T09:01:58.510Z" SessionID="32"><From><User FriendlyName="erinleecarey@aol.com (E-mail Address Not Verified)"/></From><To><User FriendlyName="James*-) I think therefore I am... I think."/></To><Text Style="font-family:MS Sans Serif; color:#000000; ">so u just wanna drop beth like a hot potatoe nice8o|</Text></Message><Message Date="5/11/2004" Time="8:02:55 PM" DateTime="2004-11-05T09:02:55.552Z" SessionID="32"><From><User FriendlyName="James*-) I think therefore I am... I think."/></From><To><User FriendlyName="erinleecarey@aol.com (E-mail Address Not Verified)"/></To><Text Style="font-family:Comic Sans MS; font-weight:bold; color:#000080; ">No...... its way 2 complex 2 explain and im making a sig so  :P</Text></Message><Message Date="5/11/2004" Time="8:03:13 PM" DateTime="2004-11-05T09:03:13.107Z" SessionID="33"><From><User FriendlyName="erinleecarey@aol.com (E-mail Address Not Verified)"/></From><To><User FriendlyName="James*-) I think therefore I am... I think."/></To><Text Style="font-family:MS Sans Serif; color:#000000; ">wats a sig?</Text></Message><Message Date="5/11/2004" Time="8:03:30 PM" DateTime="2004-11-05T09:03:30.893Z" SessionID="33"><From><User FriendlyName="James*-) I think therefore I am... I think."/></From><To><User FriendlyName="erinleecarey@aol.com (E-mail Address Not Verified)"/></To><Text Style="font-family:Comic Sans MS; font-weight:bold; color:#000080; ">a signature</Text></Message><Message Date="5/11/2004" Time="8:03:44 PM" DateTime="2004-11-05T09:03:44.532Z" SessionID="34"><From><User FriendlyName="erinleecarey@aol.com (E-mail Address Not Verified)"/></From><To><User FriendlyName="James*-) I think therefore I am... I think."/></To><Text Style="font-family:MS Sans Serif; color:#000000; ">i dont get it?</Text></Message><Message Date="5/11/2004" Time="8:04:43 PM" DateTime="2004-11-05T09:04:43.547Z" SessionID="34"><From><User FriendlyName="erinleecarey@aol.com (E-mail Address Not Verified)"/></From><To><User FriendlyName="James*-) I think therefore I am... I think."/></To><Text Style="font-family:MS Sans Serif; color:#000000; ">fine then go have no fun sumwhere else</Text></Message><Message Date="5/11/2004" Time="8:05:22 PM" DateTime="2004-11-05T09:05:22.884Z" SessionID="34"><From><User FriendlyName="James*-) I think therefore I am... I think."/></From><To><User FriendlyName="erinleecarey@aol.com (E-mail Address Not Verified)"/></To><Text Style="font-family:Comic Sans MS; font-weight:bold; color:#000080; ">....</Text></Message><Message Date="5/11/2004" Time="8:05:37 PM" DateTime="2004-11-05T09:05:37.855Z" SessionID="34"><From><User FriendlyName="James*-) I think therefore I am... I think."/></From><To><User FriendlyName="erinleecarey@aol.com (E-mail Address Not Verified)"/></To><Text Style="font-family:Comic Sans MS; font-weight:bold; color:#000080; ">Stop being a spoilt Sport :P</Text></Message><Message Date="5/11/2004" Time="8:05:50 PM" DateTime="2004-11-05T09:05:50.544Z" SessionID="35"><From><User FriendlyName="erinleecarey@aol.com (E-mail Address Not Verified)"/></From><To><User FriendlyName="James*-) I think therefore I am... I think."/></To><Text Style="font-family:MS Sans Serif; color:#000000; ">k i like sport</Text></Message><Message Date="5/11/2004" Time="8:06:09 PM" DateTime="2004-11-05T09:06:09.501Z" SessionID="35"><From><User FriendlyName="James*-) I think therefore I am... I think."/></From><To><User FriendlyName="erinleecarey@aol.com (E-mail Address Not Verified)"/></To><Text Style="font-family:Comic Sans MS; font-weight:bold; color:#000080; ">Go make daniel go out with kaitlyn.... </Text></Message><Message Date="5/11/2004" Time="8:07:50 PM" DateTime="2004-11-05T09:07:50.827Z" SessionID="36"><From><User FriendlyName="erinleecarey@aol.com (E-mail Address Not Verified)"/></From><To><User FriendlyName="James*-) I think therefore I am... I think."/></To><Text Style="font-family:MS Sans Serif; color:#000000; ">no hell ask her anyway no fun</Text></Message><Message Date="5/11/2004" Time="8:08:45 PM" DateTime="2004-11-05T09:08:45.135Z" SessionID="36"><From><User FriendlyName="James*-) I think therefore I am... I think."/></From><To><User FriendlyName="erinleecarey@aol.com (E-mail Address Not Verified)"/></To><Text Style="font-family:Comic Sans MS; font-weight:bold; color:#000080; ">/???\</Text></Message><Message Date="5/11/2004" Time="8:12:36 PM" DateTime="2004-11-05T09:12:36.277Z" SessionID="37"><From><User FriendlyName="erinleecarey@aol.com (E-mail Address Not Verified)"/></From><To><User FriendlyName="James*-) I think therefore I am... I think."/></To><Text Style="font-family:MS Sans Serif; color:#000000; ">yeah u do that</Text></Message><Message Date="5/11/2004" Time="8:12:52 PM" DateTime="2004-11-05T09:12:52.871Z" SessionID="37"><From><User FriendlyName="James*-) I think therefore I am... I think."/></From><To><User FriendlyName="erinleecarey@aol.com (E-mail Address Not Verified)"/></To><Text Style="font-family:Comic Sans MS; font-weight:bold; color:#000080; ">/???</Text></Message><Message Date="5/11/2004" Time="8:12:57 PM" DateTime="2004-11-05T09:12:57.658Z" SessionID="37"><From><User FriendlyName="James*-) I think therefore I am... I think."/></From><To><User FriendlyName="erinleecarey@aol.com (E-mail Address Not Verified)"/></To><Text Style="font-family:Comic Sans MS; font-weight:bold; color:#000080; ">Take a hint will u</Text></Message><Message Date="5/11/2004" Time="8:14:06 PM" DateTime="2004-11-05T09:14:06.767Z" SessionID="38"><From><User FriendlyName="erinleecarey@aol.com (E-mail Address Not Verified)"/></From><To><User FriendlyName="James*-) I think therefore I am... I think."/></To><Text Style="font-family:MS Sans Serif; color:#000000; ">wat that u want to lik out beth yeah i know</Text></Message><Message Date="5/11/2004" Time="8:14:23 PM" DateTime="2004-11-05T09:14:23.351Z" SessionID="38"><From><User FriendlyName="James*-) I think therefore I am... I think."/></From><To><User FriendlyName="erinleecarey@aol.com (E-mail Address Not Verified)"/></To><Text Style="font-family:Comic Sans MS; font-weight:bold; color:#000080; ">Yeah i woudn't mind ;)</Text></Message><Message Date="5/11/2004" Time="8:14:52 PM" DateTime="2004-11-05T09:14:52.192Z" SessionID="39"><From><User FriendlyName="erinleecarey@aol.com (E-mail Address Not Verified)"/></From><To><User FriendlyName="James*-) I think therefore I am... I think."/></To><Text Style="font-family:MS Sans Serif; color:#000000; ">ok this is gettin creepy</Text></Message><Message Date="5/11/2004" Time="8:15:32 PM" DateTime="2004-11-05T09:15:32.250Z" SessionID="39"><From><User FriendlyName="James*-) I think therefore I am... I think."/></From><To><User FriendlyName="erinleecarey@aol.com (E-mail Address Not Verified)"/></To><Text Style="font-family:Comic Sans MS; font-weight:bold; color:#000080; ">u sed lick no like</Text></Message><Message Date="5/11/2004" Time="8:15:35 PM" DateTime="2004-11-05T09:15:35.034Z" SessionID="39"><From><User FriendlyName="James*-) I think therefore I am... I think."/></From><To><User FriendlyName="erinleecarey@aol.com (E-mail Address Not Verified)"/></To><Text Style="font-family:Comic Sans MS; font-weight:bold; color:#000080; ">lol</Text></Message><Message Date="5/11/2004" Time="8:15:35 PM" DateTime="2004-11-05T09:15:35.775Z" SessionID="39"><From><User FriendlyName="James*-) I think therefore I am... I think."/></From><To><User FriendlyName="erinleecarey@aol.com (E-mail Address Not Verified)"/></To><Text Style="font-family:Comic Sans MS; font-weight:bold; color:#000080; ">nvm</Text></Message><Message Date="5/11/2004" Time="8:20:27 PM" DateTime="2004-11-05T09:20:27.475Z" SessionID="40"><From><User FriendlyName="James*-) I think therefore I am... I think."/></From><To><User FriendlyName="erinleecarey@aol.com (E-mail Address Not Verified)"/></To><Text Style="font-family:Comic Sans MS; font-weight:bold; color:#000080; ">Look im not gonner cuz she TOLD ME that she thinks im scary </Text></Message><Message Date="5/11/2004" Time="8:21:01 PM" DateTime="2004-11-05T09:21:01.013Z" SessionID="41"><From><User FriendlyName="James*-) I think therefore I am... I think."/></From><To><User FriendlyName="erinleecarey@aol.com (E-mail Address Not Verified)"/></To><Text Style="font-family:Comic Sans MS; font-weight:bold; color:#000080; ">And if u give me kaits number Daniel will ask hher out</Text></Message><Message Date="5/11/2004" Time="8:23:11 PM" DateTime="2004-11-05T09:23:11.891Z" SessionID="42"><From><User FriendlyName="James*-) I think therefore I am... I think."/></From><To><User FriendlyName="erinleecarey@aol.com (E-mail Address Not Verified)"/></To><Text Style="font-family:Comic Sans MS; font-weight:bold; color:#000080; ">Erin</Text></Message><Message Date="5/11/2004" Time="8:23:12 PM" DateTime="2004-11-05T09:23:12.412Z" SessionID="42"><From><User FriendlyName="James*-) I think therefore I am... I think."/></From><To><User FriendlyName="erinleecarey@aol.com (E-mail Address Not Verified)"/></To><Text Style="font-family:Comic Sans MS; font-weight:bold; color:#000080; ">ERin</Text></Message><Message Date="5/11/2004" Time="8:23:12 PM" DateTime="2004-11-05T09:23:12.862Z" SessionID="42"><From><User FriendlyName="James*-) I think therefore I am... I think."/></From><To><User FriendlyName="erinleecarey@aol.com (E-mail Address Not Verified)"/></To><Text Style="font-family:Comic Sans MS; font-weight:bold; color:#000080; ">erin</Text></Message><Message Date="5/11/2004" Time="8:23:13 PM" DateTime="2004-11-05T09:23:13.233Z" SessionID="42"><From><User FriendlyName="James*-) I think therefore I am... I think."/></From><To><User FriendlyName="erinleecarey@aol.com (E-mail Address Not Verified)"/></To><Text Style="font-family:Comic Sans MS; font-weight:bold; color:#000080; ">erin</Text></Message><Message Date="5/11/2004" Time="8:23:13 PM" DateTime="2004-11-05T09:23:13.583Z" SessionID="42"><From><User FriendlyName="James*-) I think therefore I am... I think."/></From><To><User FriendlyName="erinleecarey@aol.com (E-mail Address Not Verified)"/></To><Text Style="font-family:Comic Sans MS; font-weight:bold; color:#000080; ">erni</Text></Message><Message Date="5/11/2004" Time="8:23:13 PM" DateTime="2004-11-05T09:23:13.924Z" SessionID="42"><From><User FriendlyName="James*-) I think therefore I am... I think."/></From><To><User FriendlyName="erinleecarey@aol.com (E-mail Address Not Verified)"/></To><Text Style="font-family:Comic Sans MS; font-weight:bold; color:#000080; ">einr</Text></Message><Message Date="5/11/2004" Time="8:23:14 PM" DateTime="2004-11-05T09:23:14.264Z" SessionID="42"><From><User FriendlyName="James*-) I think therefore I am... I think."/></From><To><User FriendlyName="erinleecarey@aol.com (E-mail Address Not Verified)"/></To><Text Style="font-family:Comic Sans MS; font-weight:bold; color:#000080; ">erjnie</Text></Message><Message Date="5/11/2004" Time="8:23:14 PM" DateTime="2004-11-05T09:23:14.615Z" SessionID="42"><From><User FriendlyName="James*-) I think therefore I am... I think."/></From><To><User FriendlyName="erinleecarey@aol.com (E-mail Address Not Verified)"/></To><Text Style="font-family:Comic Sans MS; font-weight:bold; color:#000080; ">rner</Text></Message><Message Date="5/11/2004" Time="8:23:14 PM" DateTime="2004-11-05T09:23:14.975Z" SessionID="42"><From><User FriendlyName="James*-) I think therefore I am... I think."/></From><To><User FriendlyName="erinleecarey@aol.com (E-mail Address Not Verified)"/></To><Text Style="font-family:Comic Sans MS; font-weight:bold; color:#000080; ">iner</Text></Message><Message Date="5/11/2004" Time="8:23:15 PM" DateTime="2004-11-05T09:23:15.236Z" SessionID="42"><From><User FriendlyName="James*-) I think therefore I am... I think."/></From><To><User FriendlyName="erinleecarey@aol.com (E-mail Address Not Verified)"/></To><Text Style="font-family:Comic Sans MS; font-weight:bold; color:#000080; ">ejw</Text></Message><Message Date="5/11/2004" Time="8:23:15 PM" DateTime="2004-11-05T09:23:15.586Z" SessionID="42"><From><User FriendlyName="James*-) I think therefore I am... I think."/></From><To><User FriendlyName="erinleecarey@aol.com (E-mail Address Not Verified)"/></To><Text Style="font-family:Comic Sans MS; font-weight:bold; color:#000080; ">rpsijf;</Text></Message><Message Date="5/11/2004" Time="8:23:16 PM" DateTime="2004-11-05T09:23:16.067Z" SessionID="42"><From><User FriendlyName="James*-) I think therefore I am... I think."/></From><To><User FriendlyName="erinleecarey@aol.com (E-mail Address Not Verified)"/></To><Text Style="font-family:Comic Sans MS; font-weight:bold; color:#000080; ">sejpifdj</Text></Message><Message Date="5/11/2004" Time="8:23:16 PM" DateTime="2004-11-05T09:23:16.988Z" SessionID="42"><From><User FriendlyName="James*-) I think therefore I am... I think."/></From><To><User FriendlyName="erinleecarey@aol.com (E-mail Address Not Verified)"/></To><Text Style="font-family:Comic Sans MS; font-weight:bold; color:#000080; ">eerniu</Text></Message><Message Date="5/11/2004" Time="8:23:17 PM" DateTime="2004-11-05T09:23:17.549Z" SessionID="42"><From><User FriendlyName="James*-) I think therefore I am... I think."/></From><To><User FriendlyName="erinleecarey@aol.com (E-mail Address Not Verified)"/></To><Text Style="font-family:Comic Sans MS; font-weight:bold; color:#000080; ">erin</Text></Message><Message Date="5/11/2004" Time="8:23:18 PM" DateTime="2004-11-05T09:23:18.601Z" SessionID="42"><From><User FriendlyName="James*-) I think therefore I am... I think."/></From><To><User FriendlyName="erinleecarey@aol.com (E-mail Address Not Verified)"/></To><Text Style="font-family:Comic Sans MS; font-weight:bold; color:#000080; ">erin</Text></Message><Message Date="5/11/2004" Time="8:23:19 PM" DateTime="2004-11-05T09:23:19.642Z" SessionID="42"><From><User FriendlyName="James*-) I think therefore I am... I think."/></From><To><User FriendlyName="erinleecarey@aol.com (E-mail Address Not Verified)"/></To><Text Style="font-family:Comic Sans MS; font-weight:bold; color:#000080; ">ERIN!</Text></Message><Message Date="5/11/2004" Time="8:29:19 PM" DateTime="2004-11-05T09:29:19.239Z" SessionID="43"><From><User FriendlyName="erinleecarey@aol.com (E-mail Address Not Verified)"/></From><To><User FriendlyName="James*-) I think therefore I am... I think."/></To><Text Style="font-family:MS Sans Serif; color:#000000; ">i hate u suk on that</Text></Message><Message Date="5/11/2004" Time="8:36:23 PM" DateTime="2004-11-05T09:36:23.649Z" SessionID="43"><From><User FriendlyName="James*-) I think therefore I am... I think."/></From><To><User FriendlyName="erinleecarey@aol.com (E-mail Address Not Verified)"/></To><Text Style="font-family:Comic Sans MS; font-weight:bold; color:#000080; ">Oi errin</Text></Message><Message Date="5/11/2004" Time="8:36:31 PM" DateTime="2004-11-05T09:36:31.120Z" SessionID="43"><From><User FriendlyName="James*-) I think therefore I am... I think."/></From><To><User FriendlyName="erinleecarey@aol.com (E-mail Address Not Verified)"/></To><Text Style="font-family:Comic Sans MS; font-weight:bold; color:#000080; ">Daniel sed he ask out Kaitlun</Text></Message><Message Date="5/11/2004" Time="8:36:35 PM" DateTime="2004-11-05T09:36:35.206Z" SessionID="43"><From><User FriendlyName="James*-) I think therefore I am... I think."/></From><To><User FriendlyName="erinleecarey@aol.com (E-mail Address Not Verified)"/></To><Text Style="font-family:Comic Sans MS; font-weight:bold; color:#000080; ">with a y</Text></Message><Message Date="5/11/2004" Time="8:36:44 PM" DateTime="2004-11-05T09:36:44.129Z" SessionID="43"><From><User FriendlyName="James*-) I think therefore I am... I think."/></From><To><User FriendlyName="erinleecarey@aol.com (E-mail Address Not Verified)"/></To><Text Style="font-family:Comic Sans MS; font-weight:bold; color:#000080; ">if u give me her number</Text></Message><Message Date="5/11/2004" Time="8:37:17 PM" DateTime="2004-11-05T09:37:17.807Z" SessionID="43"><From><User FriendlyName="erinleecarey@aol.com (E-mail Address Not Verified)"/></From><To><User FriendlyName="James*-) I think therefore I am... I think."/></To><Text Style="font-family:MS Sans Serif; color:#000000; ">i dont have it im at paiges</Text></Message><Message Date="5/11/2004" Time="8:37:43 PM" DateTime="2004-11-05T09:37:43.875Z" SessionID="43"><From><User FriendlyName="James*-) I think therefore I am... I think."/></From><To><User FriendlyName="erinleecarey@aol.com (E-mail Address Not Verified)"/></To><Text Style="font-family:Comic Sans MS; font-weight:bold; color:#000080; ">^o)</Text></Message><Message Date="5/11/2004" Time="8:37:59 PM" DateTime="2004-11-05T09:37:59.317Z" SessionID="43"><From><User FriendlyName="James*-) I think therefore I am... I think."/></From><To><User FriendlyName="erinleecarey@aol.com (E-mail Address Not Verified)"/></To><Text Style="font-family:Comic Sans MS; font-weight:bold; color:#000080; ">uhhh ok</Text></Message><Message Date="5/11/2004" Time="8:39:29 PM" DateTime="2004-11-05T09:39:29.316Z" SessionID="44"><From><User FriendlyName="erinleecarey@aol.com (E-mail Address Not Verified)"/></From><To><User FriendlyName="James*-) I think therefore I am... I think."/></To><Text Style="font-family:MS Sans Serif; color:#000000; ">i am</Text></Message><Message Date="5/11/2004" Time="8:39:41 PM" DateTime="2004-11-05T09:39:41.584Z" SessionID="44"><From><User FriendlyName="erinleecarey@aol.com (E-mail Address Not Verified)"/></From><To><User FriendlyName="James*-) I think therefore I am... I think."/></To><Text Style="font-family:MS Sans Serif; color:#000000; ">paige hood u know in our yr</Text></Message><Message Date="5/11/2004" Time="8:39:50 PM" DateTime="2004-11-05T09:39:50.397Z" SessionID="44"><From><User FriendlyName="James*-) I think therefore I am... I think."/></From><To><User FriendlyName="erinleecarey@aol.com (E-mail Address Not Verified)"/></To><Text Style="font-family:Comic Sans MS; font-weight:bold; color:#000080; ">yes I am aware</Text></Message><Message Date="5/11/2004" Time="8:42:56 PM" DateTime="2004-11-05T09:42:56.614Z" SessionID="45"><From><User FriendlyName="erinleecarey@aol.com (E-mail Address Not Verified)"/></From><To><User FriendlyName="James*-) I think therefore I am... I think."/></To><Text Style="font-family:MS Sans Serif; color:#000000; ">cya</Text></Message><Message Date="5/11/2004" Time="8:44:54 PM" DateTime="2004-11-05T09:44:54.734Z" SessionID="45"><From><User FriendlyName="James*-) I think therefore I am... I think."/></From><To><User FriendlyName="erinleecarey@aol.com (E-mail Address Not Verified)"/></To><Text Style="font-family:Comic Sans MS; font-weight:bold; color:#000080; ">Adios</Text></Message><Message Date="7/11/2004" Time="5:59:40 PM" DateTime="2004-11-07T06:59:40.213Z" SessionID="46"><From><User FriendlyName="James*-) I think therefore I am... I think."/></From><To><User FriendlyName="erinleecarey@aol.com (E-mail Address Not Verified)"/></To><Text Style="font-family:Comic Sans MS; font-weight:bold; color:#000080; ">Helllo</Text></Message><Message Date="7/11/2004" Time="6:04:11 PM" DateTime="2004-11-07T07:04:11.093Z" SessionID="47"><From><User FriendlyName="erinleecarey@aol.com (E-mail Address Not Verified)"/></From><To><User FriendlyName="James*-) I think therefore I am... I think."/></To><Text Style="font-family:Papyrus; font-weight:bold; color:#ff00ff; ">sorry my computer is stuffin up</Text></Message><Message Date="7/11/2004" Time="6:04:44 PM" DateTime="2004-11-07T07:04:44.761Z" SessionID="47"><From><User FriendlyName="erinleecarey@aol.com (E-mail Address Not Verified)"/></From><To><User FriendlyName="James*-) I think therefore I am... I think."/></To><Text Style="font-family:Papyrus; font-weight:bold; color:#ff00ff; ">....................</Text></Message><Message Date="7/11/2004" Time="6:04:57 PM" DateTime="2004-11-07T07:04:57.359Z" SessionID="47"><From><User FriendlyName="erinleecarey@aol.com (E-mail Address Not Verified)"/></From><To><User FriendlyName="James*-) I think therefore I am... I think."/></To><Text Style="font-family:Papyrus; font-weight:bold; color:#ff00ff; ">fine then go have no fun sumwhere els</Text></Message><Message Date="7/11/2004" Time="6:05:07 PM" DateTime="2004-11-07T07:05:07.914Z" SessionID="47"><From><User FriendlyName="erinleecarey@aol.com (E-mail Address Not Verified)"/></From><To><User FriendlyName="James*-) I think therefore I am... I think."/></To><Text Style="font-family:Papyrus; font-weight:bold; color:#ff00ff; ">cya later sparky</Text></Message><Message Date="7/11/2004" Time="6:07:04 PM" DateTime="2004-11-07T07:07:04.973Z" SessionID="47"><From><User FriendlyName="erinleecarey@aol.com (E-mail Address Not Verified)"/></From><To><User FriendlyName="James*-) I think therefore I am... I think."/></To><Text Style="font-family:Papyrus; font-weight:bold; color:#ff00ff; ">.....................</Text></Message><Message Date="7/11/2004" Time="6:08:50 PM" DateTime="2004-11-07T07:08:50.384Z" SessionID="47"><From><User FriendlyName="erinleecarey@aol.com (E-mail Address Not Verified)"/></From><To><User FriendlyName="James*-) I think therefore I am... I think."/></To><Text Style="font-family:Papyrus; font-weight:bold; color:#ff00ff; ">talk to me dikhead</Text></Message><Message Date="7/11/2004" Time="6:30:20 PM" DateTime="2004-11-07T07:30:20.289Z" SessionID="47"><From><User FriendlyName="erinleecarey@aol.com (E-mail Address Not Verified)"/></From><To><User FriendlyName="James*-) I think therefore I am... I think."/></To><Text Style="font-family:Papyrus; font-weight:bold; color:#ff00ff; ">.....................</Text></Message><Message Date="7/11/2004" Time="7:22:49 PM" DateTime="2004-11-07T08:22:49.277Z" SessionID="48"><From><User FriendlyName="erinleecarey@aol.com (E-mail Address Not Verified)"/></From><To><User FriendlyName="James*-) I think therefore I am... I think."/></To><Text Style="font-family:Papyrus; font-weight:bold; color:#ff00ff; ">hey dikhead</Text></Message><Message Date="7/11/2004" Time="7:23:47 PM" DateTime="2004-11-07T08:23:47.070Z" SessionID="48"><From><User FriendlyName="James*-) I think therefore I am... I think."/></From><To><User FriendlyName="erinleecarey@aol.com (E-mail Address Not Verified)"/></To><Text Style="font-family:Comic Sans MS; font-weight:bold; color:#000080; ">ermmhm, hello</Text></Message><Message Date="7/11/2004" Time="7:23:50 PM" DateTime="2004-11-07T08:23:50.946Z" SessionID="48"><From><User FriendlyName="James*-) I think therefore I am... I think."/></From><To><User FriendlyName="erinleecarey@aol.com (E-mail Address Not Verified)"/></To><Text Style="font-family:Comic Sans MS; font-weight:bold; color:#000080; ">Im busy soz cant talk</Text></Message><Message Date="14/01/2005" Time="7:07:41 PM" DateTime="2005-01-14T08:07:41.408Z" SessionID="49"><From><User FriendlyName="erinleecarey@aol.com (E-mail Address Not Verified)"/></From><To><User FriendlyName="(f)James *-) Not all those who wonder are lost....."/></To><Text Style="font-family:MS Shell Dlg; color:#000000; ">hey</Text></Message><Message Date="14/01/2005" Time="7:09:51 PM" DateTime="2005-01-14T08:09:51.164Z" SessionID="49"><From><User FriendlyName="(f)James *-) Not all those who wonder are lost....."/></From><To><User FriendlyName="erinleecarey@aol.com (E-mail Address Not Verified)"/></To><Text Style="font-family:Comic Sans MS; font-weight:bold; color:#000080; ">hello</Text></Message><Message Date="14/01/2005" Time="7:09:53 PM" DateTime="2005-01-14T08:09:53.047Z" SessionID="49"><From><User FriendlyName="(f)James *-) Not all those who wonder are lost....."/></From><To><User FriendlyName="erinleecarey@aol.com (E-mail Address Not Verified)"/></To><Text Style="font-family:Comic Sans MS; font-weight:bold; color:#000080; ">:(</Text></Message><Message Date="14/01/2005" Time="7:09:58 PM" DateTime="2005-01-14T08:09:58.715Z" SessionID="49"><From><User FriendlyName="erinleecarey@aol.com (E-mail Address Not Verified)"/></From><To><User FriendlyName="(f)James *-) Not all those who wonder are lost....."/></To><Text Style="font-family:MS Shell Dlg; color:#000000; ">watz rong?</Text></Message><Message Date="14/01/2005" Time="7:10:05 PM" DateTime="2005-01-14T08:10:05.335Z" SessionID="49"><From><User FriendlyName="erinleecarey@aol.com (E-mail Address Not Verified)"/></From><To><User FriendlyName="(f)James *-) Not all those who wonder are lost....."/></To><Text Style="font-family:MS Shell Dlg; color:#000000; ">diz aint erin im her frnd</Text></Message><Message Date="14/01/2005" Time="7:10:18 PM" DateTime="2005-01-14T08:10:18.764Z" SessionID="49"><From><User FriendlyName="erinleecarey@aol.com (E-mail Address Not Verified)"/></From><To><User FriendlyName="(f)James *-) Not all those who wonder are lost....."/></To><Text Style="font-family:MS Shell Dlg; color:#000000; ">watz ur last name.. i used to go to inaburra</Text></Message><Message Date="14/01/2005" Time="7:14:02 PM" DateTime="2005-01-14T08:14:02.045Z" SessionID="49"><From><User FriendlyName="(f)James *-) Not all those who wonder are lost....."/></From><To><User FriendlyName="erinleecarey@aol.com (E-mail Address Not Verified)"/></To><Text Style="font-family:Comic Sans MS; font-weight:bold; color:#000080; ">O'Toole</Text></Message><Message Date="14/01/2005" Time="7:14:09 PM" DateTime="2005-01-14T08:14:09.896Z" SessionID="49"><From><User FriendlyName="(f)James *-) Not all those who wonder are lost....."/></From><To><User FriendlyName="erinleecarey@aol.com (E-mail Address Not Verified)"/></To><Text Style="font-family:Comic Sans MS; font-weight:bold; color:#000080; ">Is this the wrestling girl ???</Text></Message><Message Date="14/01/2005" Time="7:14:19 PM" DateTime="2005-01-14T08:14:19.640Z" SessionID="49"><From><User FriendlyName="erinleecarey@aol.com (E-mail Address Not Verified)"/></From><To><User FriendlyName="(f)James *-) Not all those who wonder are lost....."/></To><Text Style="font-family:MS Shell Dlg; color:#000000; ">wat?</Text></Message><Message Date="14/01/2005" Time="7:14:22 PM" DateTime="2005-01-14T08:14:22.635Z" SessionID="49"><From><User FriendlyName="erinleecarey@aol.com (E-mail Address Not Verified)"/></From><To><User FriendlyName="(f)James *-) Not all those who wonder are lost....."/></To><Text Style="font-family:MS Shell Dlg; color:#000000; ">lol wrestlin?</Text></Message><Message Date="14/01/2005" Time="7:14:34 PM" DateTime="2005-01-14T08:14:34.792Z" SessionID="49"><From><User FriendlyName="erinleecarey@aol.com (E-mail Address Not Verified)"/></From><To><User FriendlyName="(f)James *-) Not all those who wonder are lost....."/></To><Text Style="font-family:MS Shell Dlg; color:#000000; ">lol.. im luisa</Text></Message><Message Date="14/01/2005" Time="7:14:44 PM" DateTime="2005-01-14T08:14:44.326Z" SessionID="49"><From><User FriendlyName="erinleecarey@aol.com (E-mail Address Not Verified)"/></From><To><User FriendlyName="(f)James *-) Not all those who wonder are lost....."/></To><Text Style="font-family:MS Shell Dlg; color:#000000; ">i used to lyk wrestlin but okai</Text></Message><Message Date="14/01/2005" Time="7:14:54 PM" DateTime="2005-01-14T08:14:54.841Z" SessionID="49"><From><User FriendlyName="(f)James *-) Not all those who wonder are lost....."/></From><To><User FriendlyName="erinleecarey@aol.com (E-mail Address Not Verified)"/></To><Text Style="font-family:Comic Sans MS; font-weight:bold; color:#000080; ">tYeah i thought so</Text></Message><Message Date="14/01/2005" Time="7:15:00 PM" DateTime="2005-01-14T08:15:00.669Z" SessionID="49"><From><User FriendlyName="(f)James *-) Not all those who wonder are lost....."/></From><To><User FriendlyName="erinleecarey@aol.com (E-mail Address Not Verified)"/></To><Text Style="font-family:Comic Sans MS; font-weight:bold; color:#000080; ">U always remined me heaps of erin</Text></Message><Message Date="14/01/2005" Time="7:15:03 PM" DateTime="2005-01-14T08:15:03.894Z" SessionID="49"><From><User FriendlyName="(f)James *-) Not all those who wonder are lost....."/></From><To><User FriendlyName="erinleecarey@aol.com (E-mail Address Not Verified)"/></To><Text Style="font-family:Comic Sans MS; font-weight:bold; color:#000080; ">:-O Creapy</Text></Message><Message Date="14/01/2005" Time="7:15:10 PM" DateTime="2005-01-14T08:15:10.524Z" SessionID="49"><From><User FriendlyName="erinleecarey@aol.com (E-mail Address Not Verified)"/></From><To><User FriendlyName="(f)James *-) Not all those who wonder are lost....."/></To><Text Style="font-family:MS Shell Dlg; color:#000000; ">lol</Text></Message><Message Date="14/01/2005" Time="7:15:20 PM" DateTime="2005-01-14T08:15:20.037Z" SessionID="49"><From><User FriendlyName="erinleecarey@aol.com (E-mail Address Not Verified)"/></From><To><User FriendlyName="(f)James *-) Not all those who wonder are lost....."/></To><Text Style="font-family:MS Shell Dlg; color:#000000; ">add my email so we can talk</Text></Message><Message Date="14/01/2005" Time="7:15:28 PM" DateTime="2005-01-14T08:15:28.700Z" SessionID="49"><From><User FriendlyName="erinleecarey@aol.com (E-mail Address Not Verified)"/></From><To><User FriendlyName="(f)James *-) Not all those who wonder are lost....."/></To><Text Style="font-family:MS Shell Dlg; color:#000000; ">wisi_luvs_levi@hotmail.com</Text></Message><Message Date="14/01/2005" Time="7:16:10 PM" DateTime="2005-01-14T08:16:10.690Z" SessionID="49"><From><User FriendlyName="(f)James *-) Not all those who wonder are lost....."/></From><To><User FriendlyName="erinleecarey@aol.com (E-mail Address Not Verified)"/></To><Text Style="font-family:Comic Sans MS; font-weight:bold; color:#000080; "> Okeydokey</Text></Message><Message Date="14/01/2005" Time="7:16:11 PM" DateTime="2005-01-14T08:16:11.371Z" SessionID="49"><From><User FriendlyName="(f)James *-) Not all those who wonder are lost....."/></From><To><User FriendlyName="erinleecarey@aol.com (E-mail Address Not Verified)"/></To><Text Style="font-family:Comic Sans MS; font-weight:bold; color:#000080; ">dun</Text></Message><Message Date="14/01/2005" Time="7:16:18 PM" DateTime="2005-01-14T08:16:18.441Z" SessionID="49"><From><User FriendlyName="erinleecarey@aol.com (E-mail Address Not Verified)"/></From><To><User FriendlyName="(f)James *-) Not all those who wonder are lost....."/></To><Text Style="font-family:MS Shell Dlg; color:#000000; ">daz cool</Text></Message><Message Date="14/01/2005" Time="7:16:27 PM" DateTime="2005-01-14T08:16:27.394Z" SessionID="49"><From><User FriendlyName="erinleecarey@aol.com (E-mail Address Not Verified)"/></From><To><User FriendlyName="(f)James *-) Not all those who wonder are lost....."/></To><Text Style="font-family:MS Shell Dlg; color:#000000; ">so!!!  how do u memba me man i hardli memba u</Text></Message><Message Date="14/01/2005" Time="7:16:42 PM" DateTime="2005-01-14T08:16:42.656Z" SessionID="49"><From><User FriendlyName="erinleecarey@aol.com (E-mail Address Not Verified)"/></From><To><User FriendlyName="(f)James *-) Not all those who wonder are lost....."/></To><Text Style="font-family:MS Shell Dlg; color:#000000; ">lol i waz tryin to memba u frum tha foto.. but u look lyk mah bro lyk dat</Text></Message><Message Date="14/01/2005" Time="7:17:24 PM" DateTime="2005-01-14T08:17:24.056Z" SessionID="49"><From><User FriendlyName="(f)James *-) Not all those who wonder are lost....."/></From><To><User FriendlyName="erinleecarey@aol.com (E-mail Address Not Verified)"/></To><Text Style="font-family:Comic Sans MS; font-weight:bold; color:#000080; ">lol my evil pick</Text></Message><Message Date="14/01/2005" Time="7:17:28 PM" DateTime="2005-01-14T08:17:28.883Z" SessionID="49"><From><User FriendlyName="(f)James *-) Not all those who wonder are lost....."/></From><To><User FriendlyName="erinleecarey@aol.com (E-mail Address Not Verified)"/></To><Text Style="font-family:Comic Sans MS; font-weight:bold; color:#000080; ">Thats my hat by the way</Text></Message><Message Date="14/01/2005" Time="7:17:35 PM" DateTime="2005-01-14T08:17:35.262Z" SessionID="49"><From><User FriendlyName="erinleecarey@aol.com (E-mail Address Not Verified)"/></From><To><User FriendlyName="(f)James *-) Not all those who wonder are lost....."/></To><Text Style="font-family:MS Shell Dlg; color:#000000; ">LOL</Text></Message><Message Date="14/01/2005" Time="7:17:41 PM" DateTime="2005-01-14T08:17:41.110Z" SessionID="49"><From><User FriendlyName="erinleecarey@aol.com (E-mail Address Not Verified)"/></From><To><User FriendlyName="(f)James *-) Not all those who wonder are lost....."/></To><Text Style="font-family:MS Shell Dlg; color:#000000; ">omg i hardli memba u at all man</Text></Message><Message Date="14/01/2005" Time="7:17:43 PM" DateTime="2005-01-14T08:17:43.554Z" SessionID="49"><From><User FriendlyName="erinleecarey@aol.com (E-mail Address Not Verified)"/></From><To><User FriendlyName="(f)James *-) Not all those who wonder are lost....."/></To><Text Style="font-family:MS Shell Dlg; color:#000000; ">wana c me</Text></Message><Message Date="14/01/2005" Time="7:17:57 PM" DateTime="2005-01-14T08:17:57.854Z" SessionID="49"><From><User FriendlyName="(f)James *-) Not all those who wonder are lost....."/></From><To><User FriendlyName="erinleecarey@aol.com (E-mail Address Not Verified)"/></To><Text Style="font-family:Comic Sans MS; font-weight:bold; color:#000080; ">lol yeah I rember u from yr 6 but that was age ago</Text></Message><Message Date="14/01/2005" Time="7:18:35 PM" DateTime="2005-01-14T08:18:35.859Z" SessionID="49"><From><User FriendlyName="erinleecarey@aol.com (E-mail Address Not Verified)"/></From><To><User FriendlyName="(f)James *-) Not all those who wonder are lost....."/></To><Text Style="font-family:MS Shell Dlg; color:#000000; ">oi its erin now show her the foto of the foam berd thats funny anf the foam hair </Text></Message><Message Date="14/01/2005" Time="7:18:53 PM" DateTime="2005-01-14T08:18:53.544Z" SessionID="49"><From><User FriendlyName="erinleecarey@aol.com (E-mail Address Not Verified)"/></From><To><User FriendlyName="(f)James *-) Not all those who wonder are lost....."/></To><Text Style="font-family:MS Shell Dlg; color:#000000; ">derz me ( luisa )</Text></Message><Message Date="14/01/2005" Time="7:19:07 PM" DateTime="2005-01-14T08:19:07.284Z" SessionID="49"><From><User FriendlyName="(f)James *-) Not all those who wonder are lost....."/></From><To><User FriendlyName="erinleecarey@aol.com (E-mail Address Not Verified)"/></To><Text Style="font-family:Comic Sans MS; font-weight:bold; color:#000080; ">ok changing............now</Text></Message><Message Date="14/01/2005" Time="7:19:21 PM" DateTime="2005-01-14T08:19:21.845Z" SessionID="49"><From><User FriendlyName="(f)James *-) Not all those who wonder are lost....."/></From><To><User FriendlyName="erinleecarey@aol.com (E-mail Address Not Verified)"/></To><Text Style="font-family:Comic Sans MS; font-weight:bold; color:#000080; ">WCool</Text></Message><Message Date="14/01/2005" Time="7:19:26 PM" DateTime="2005-01-14T08:19:26.011Z" SessionID="49"><From><User FriendlyName="(f)James *-) Not all those who wonder are lost....."/></From><To><User FriendlyName="erinleecarey@aol.com (E-mail Address Not Verified)"/></To><Text Style="font-family:Comic Sans MS; font-weight:bold; color:#000080; ">U look all old :-O</Text></Message><Message Date="14/01/2005" Time="7:19:34 PM" DateTime="2005-01-14T08:19:34.323Z" SessionID="49"><From><User FriendlyName="(f)James *-) Not all those who wonder are lost....."/></From><To><User FriendlyName="erinleecarey@aol.com (E-mail Address Not Verified)"/></To><Text Style="font-family:Comic Sans MS; font-weight:bold; color:#000080; ">lol Oh well it happends</Text></Message><Message Date="14/01/2005" Time="7:19:39 PM" DateTime="2005-01-14T08:19:39.440Z" SessionID="49"><From><User FriendlyName="erinleecarey@aol.com (E-mail Address Not Verified)"/></From><To><User FriendlyName="(f)James *-) Not all those who wonder are lost....."/></To><Text Style="font-family:MS Shell Dlg; color:#000000; ">THNKZ ALOT</Text></Message><Message Date="14/01/2005" Time="7:19:40 PM" DateTime="2005-01-14T08:19:40.201Z" SessionID="49"><From><User FriendlyName="erinleecarey@aol.com (E-mail Address Not Verified)"/></From><To><User FriendlyName="(f)James *-) Not all those who wonder are lost....."/></To><Text Style="font-family:MS Shell Dlg; color:#000000; ">lol</Text></Message><Message Date="14/01/2005" Time="7:20:02 PM" DateTime="2005-01-14T08:20:02.083Z" SessionID="49"><From><User FriendlyName="erinleecarey@aol.com (E-mail Address Not Verified)"/></From><To><User FriendlyName="(f)James *-) Not all those who wonder are lost....."/></To><Text Style="font-family:MS Shell Dlg; color:#000000; ">show me tha foam hair</Text></Message><Message Date="14/01/2005" Time="7:20:09 PM" DateTime="2005-01-14T08:20:09.634Z" SessionID="49"><From><User FriendlyName="(f)James *-) Not all those who wonder are lost....."/></From><To><User FriendlyName="erinleecarey@aol.com (E-mail Address Not Verified)"/></To><Text Style="font-family:Comic Sans MS; font-weight:bold; color:#000080; ">Its up...</Text></Message><Message Date="14/01/2005" Time="7:20:20 PM" DateTime="2005-01-14T08:20:20.589Z" SessionID="49"><From><User FriendlyName="(f)James *-) Not all those who wonder are lost....."/></From><To><User FriendlyName="erinleecarey@aol.com (E-mail Address Not Verified)"/></To><Text Style="font-family:Comic Sans MS; font-weight:bold; color:#000080; ">Might still be loading</Text></Message><Message Date="14/01/2005" Time="7:20:25 PM" DateTime="2005-01-14T08:20:25.026Z" SessionID="49"><From><User FriendlyName="erinleecarey@aol.com (E-mail Address Not Verified)"/></From><To><User FriendlyName="(f)James *-) Not all those who wonder are lost....."/></To><Text Style="font-family:MS Shell Dlg; color:#000000; ">yeh</Text></Message><Message Date="14/01/2005" Time="7:21:40 PM" DateTime="2005-01-14T08:21:40.464Z" SessionID="49"><From><User FriendlyName="erinleecarey@aol.com (E-mail Address Not Verified)"/></From><To><User FriendlyName="(f)James *-) Not all those who wonder are lost....."/></To><Text Style="font-family:MS Shell Dlg; color:#000000; ">do u hav matt s' email</Text></Message><Message Date="14/01/2005" Time="7:21:56 PM" DateTime="2005-01-14T08:21:56.778Z" SessionID="49"><From><User FriendlyName="erinleecarey@aol.com (E-mail Address Not Verified)"/></From><To><User FriendlyName="(f)James *-) Not all those who wonder are lost....."/></To><Text Style="font-family:MS Shell Dlg; color:#000000; ">wait ill go on me email</Text></Message></Log>
